Workbook

Sheet Pricing Worksheet
B2: Project name | E2: Project address | H2: Quote # | K2: Person Quoting | N2: Person who checked quote | Q2: 3.20.25 - 182 Robinson St - Mike Vetzal - Glass Flooring Systems Proposal #17717 Distributor Pricing | R2: Residential
B3: Contact | E3: Contact address | H3: Contact phone | K3: Contact email | L3: mailto:mvetzal@bapgroup.ca | R3: Commercial
B4: Project Type | E4: Architect | H4: Homeowner | K4: Drafter/Designer
B5: Fill in yellow cells only. All other cells will calculate automatically
B6: Surfaces | C6: Cost/Unit $ | D6: =B113 | G6: =B114 | J6: =B115 | M6: =B116 | P6: =B117 | S6: =B118 | V6: =B119 | Y6: =B120 | AB6: =B121 | AE6: =B122 | AH6: Subtotal $
C7: Do not erase | E7: Qty | F7: Price | H7: Qty | I7: Price | K7: Qty | L7: Price | N7: Qty | O7: Price | Q7: Qty | R7: Price | T7: Qty | U7: Price | W7: Qty | X7: Price | Z7: Qty | AA7: Price | AC7: Qty | AD7: Price | AF7: Qty | AG7: Price
B8: Glass
B9: Glass - no IGU | C9: 66 | E9: =IF(D9="y",$H$113,0) | F9: =E9*$C9 | H9: =IF(G9="y",$H$114,0) | I9: =H9*$C9 | K9: =IF(J9="y",$H$115,0) | L9: =K9*$C9 | N9: =IF(M9="y",$H$116,0) | O9: =N9*$C9 | Q9: =IF(P9="y",$H$117,0) | R9: =Q9*$C9 | T9: =IF(S9="y",$H$118,0) | U9: =T9*$C9 | W9: =IF(V9="y",$H$119,0) | X9: =W9*$C9 | Z9: =IF(Y9="y",$H$120,0) | AA9: =Z9*$C9 | AC9: =IF(AB9="y",$H$121,0) | AD9: =AC9*$C9 | AF9: =IF(AE9="y",$H$122,0) | AG9: =AF9*$C9 | AH9: =SUM(F9+I9+L9+O9+R9+U9+X9+AA9+AD9+AG9)
B10: Glass - with IGU | C10: 112 | E10: =IF(D10="y",$H$113,0) | F10: =E10*$C10 | H10: =IF(G10="y",$H$114,0) | I10: =H10*$C10 | K10: =IF(J10="y",$H$115,0) | L10: =K10*$C10 | N10: =IF(M10="y",$H$116,0) | O10: =N10*$C10 | Q10: =IF(P10="y",$H$117,0) | R10: =Q10*$C10 | T10: =IF(S10="y",$H$118,0) | U10: =T10*$C10 | W10: =IF(V10="y",$H$119,0) | X10: =W10*$C10 | Z10: =IF(Y10="y",$H$120,0) | AA10: =Z10*$C10 | AC10: =IF(AB10="y",$H$121,0) | AD10: =AC10*$C10 | AF10: =IF(AE10="y",$H$122,0) | AG10: =AF10*$C10 | AH10: =SUM(F10+I10+L10+O10+R10+U10+X10+AA10+AD10+AG10)
B11: Glass 2.0 system | C11: 121 | E11: =IF(D11="y",$H$113,0) | F11: =E11*$C11 | H11: =IF(G11="y",$H$114,0) | I11: =H11*$C11 | K11: =IF(J11="y",$H$115,0) | L11: =K11*$C11 | N11: =IF(M11="y",$H$116,0) | O11: =N11*$C11 | Q11: =IF(P11="y",$H$117,0) | R11: =Q11*$C11 | T11: =IF(S11="y",$H$118,0) | U11: =T11*$C11 | W11: =IF(V11="y",$H$119,0) | X11: =W11*$C11 | Z11: =IF(Y11="y",$H$120,0) | AA11: =Z11*$C11 | AC11: =IF(AB11="y",$H$121,0) | AD11: =AC11*$C11 | AF11: =IF(AE11="y",$H$122,0) | AG11: =AF11*$C11 | AH11: =SUM(F11+I11+L11+O11+R11+U11+X11+AA11+AD11+AG11)
B12: Stair treads - post lamination polish | C12: 99 | E12: =IF(D12="y",$H$113,0) | F12: =E12*$C12 | H12: =IF(G12="y",$H$114,0) | I12: =H12*$C12 | K12: =IF(J12="y",$H$115,0) | L12: =K12*$C12 | N12: =IF(M12="y",$H$116,0) | O12: =N12*$C12 | Q12: =IF(P12="y",$H$117,0) | R12: =Q12*$C12 | T12: =IF(S12="y",$H$118,0) | U12: =T12*$C12 | W12: =IF(V12="y",$H$119,0) | X12: =W12*$C12 | Z12: =IF(Y12="y",$H$120,0) | AA12: =Z12*$C12 | AC12: =IF(AB12="y",$H$121,0) | AD12: =AC12*$C12 | AF12: =IF(AE12="y",$H$122,0) | AG12: =AF12*$C12 | AH12: =SUM(F12+I12+L12+O12+R12+U12+X12+AA12+AD12+AG12)
B13: Non-Walkable glass | C13: 71 | E13: =IF(D13="y",$H$113,0) | F13: =E13*$C13 | H13: =IF(G13="y",$H$114,0) | I13: =H13*$C13 | K13: =IF(J13="y",$H$115,0) | L13: =K13*$C13 | N13: =IF(M13="y",$H$116,0) | O13: =N13*$C13 | Q13: =IF(P13="y",$H$117,0) | R13: =Q13*$C13 | T13: =IF(S13="y",$H$118,0) | U13: =T13*$C13 | W13: =IF(V13="y",$H$119,0) | X13: =W13*$C13 | Z13: =IF(Y13="y",$H$120,0) | AA13: =Z13*$C13 | AC13: =IF(AB13="y",$H$121,0) | AD13: =AC13*$C13 | AF13: =IF(AE13="y",$H$122,0) | AG13: =AF13*$C13 | AH13: =SUM(F13+I13+L13+O13+R13+U13+X13+AA13+AD13+AG13)
B14: EGR | C14: 95 | E14: =IF(D14="y",$H$113,0) | F14: =E14*$C14 | H14: =IF(G14="y",$H$114,0) | I14: =H14*$C14 | K14: =IF(J14="y",$H$115,0) | L14: =K14*$C14 | N14: =IF(M14="y",$H$116,0) | O14: =N14*$C14 | Q14: =IF(P14="y",$H$117,0) | R14: =Q14*$C14 | T14: =IF(S14="y",$H$118,0) | U14: =T14*$C14 | W14: =IF(V14="y",$H$119,0) | X14: =W14*$C14 | Z14: =IF(Y14="y",$H$120,0) | AA14: =Z14*$C14 | AC14: =IF(AB14="y",$H$121,0) | AD14: =AC14*$C14 | AF14: =IF(AE14="y",$H$122,0) | AG14: =AF14*$C14 | AH14: =SUM(F14+I14+L14+O14+R14+U14+X14+AA14+AD14+AG14)
B15: Options
B16: Sentry Glass interlayer | C16: 4 | E16: =IF(D16="y",$H$113,0) | F16: =E16*$C16 | H16: =IF(G16="y",$H$114,0) | I16: =H16*$C16 | K16: =IF(J16="y",$H$115,0) | L16: =K16*$C16 | N16: =IF(M16="y",$H$116,0) | O16: =N16*$C16 | Q16: =IF(P16="y",$H$117,0) | R16: =Q16*$C16 | T16: =IF(S16="y",$H$118,0) | U16: =T16*$C16 | W16: =IF(V16="y",$H$119,0) | X16: =W16*$C16 | Z16: =IF(Y16="y",$H$120,0) | AA16: =Z16*$C16 | AC16: =IF(AB16="y",$H$121,0) | AD16: =AC16*$C16 | AF16: =IF(AE16="y",$H$122,0) | AG16: =AF16*$C16 | AH16: =SUM(F16+I16+L16+O16+R16+U16+X16+AA16+AD16+AG16)
B17: Colored interlayer | C17: 10 | E17: =IF(D17="y",$H$113,0) | F17: =E17*$C17 | H17: =IF(G17="y",$H$114,0) | I17: =H17*$C17 | K17: =IF(J17="y",$H$115,0) | L17: =K17*$C17 | N17: =IF(M17="y",$H$116,0) | O17: =N17*$C17 | Q17: =IF(P17="y",$H$117,0) | R17: =Q17*$C17 | T17: =IF(S17="y",$H$118,0) | U17: =T17*$C17 | W17: =IF(V17="y",$H$119,0) | X17: =W17*$C17 | Z17: =IF(Y17="y",$H$120,0) | AA17: =Z17*$C17 | AC17: =IF(AB17="y",$H$121,0) | AD17: =AC17*$C17 | AF17: =IF(AE17="y",$H$122,0) | AG17: =AF17*$C17 | AH17: =SUM(F17+I17+L17+O17+R17+U17+X17+AA17+AD17+AG17)
B18: Switchable Glass | C18: 25 | E18: =IF(D18="y",$H$113,0) | F18: =E18*$C18 | H18: =IF(G18="y",$H$114,0) | I18: =H18*$C18 | K18: =IF(J18="y",$H$115,0) | L18: =K18*$C18 | N18: =IF(M18="y",$H$116,0) | O18: =N18*$C18 | Q18: =IF(P18="y",$H$117,0) | R18: =Q18*$C18 | T18: =IF(S18="y",$H$118,0) | U18: =T18*$C18 | W18: =IF(V18="y",$H$119,0) | X18: =W18*$C18 | Z18: =IF(Y18="y",$H$120,0) | AA18: =Z18*$C18 | AC18: =IF(AB18="y",$H$121,0) | AD18: =AC18*$C18 | AF18: =IF(AE18="y",$H$122,0) | AG18: =AF18*$C18 | AH18: =SUM(F18+I18+L18+O18+R18+U18+X18+AA18+AD18+AG18)
B19: Backpaint - Add for all expedited orders | C19: 7.5 | E19: =IF(D19="y",E64+E65,0) | F19: =E19*$C19 | H19: =IF(G19="y",H64+H65,0) | I19: =H19*$C19 | K19: =IF(J19="y",K64+K65,0) | L19: =K19*$C19 | N19: =IF(M19="y",N64+N65,0) | O19: =N19*$C19 | Q19: =IF(P19="y",Q64+Q65,0) | R19: =Q19*$C19 | T19: =IF(S19="y",T64+T65,0) | U19: =T19*$C19 | W19: =IF(V19="y",W64+W65,0) | X19: =W19*$C19 | Z19: =IF(Y19="y",Z64+Z65,0) | AA19: =Z19*$C19 | AC19: =IF(AB19="y",AC64+AC65,0) | AD19: =AC19*$C19 | AF19: =IF(AE19="y",AF64+AF65,0) | AG19: =AF19*$C19 | AH19: =SUM(F19+I19+L19+O19+R19+U19+X19+AA19+AD19+AG19)
B20: Custom | C20: 20 | E20: =IF(D20="y",$H$113,0) | F20: =E20*$C20 | H20: =IF(G20="y",$H$114,0) | I20: =H20*$C20 | K20: =IF(J20="y",$H$115,0) | L20: =K20*$C20 | N20: =IF(M20="y",$H$116,0) | O20: =N20*$C20 | Q20: =IF(P20="y",$H$117,0) | R20: =Q20*$C20 | T20: =IF(S20="y",$H$118,0) | U20: =T20*$C20 | W20: =IF(V20="y",$H$119,0) | X20: =W20*$C20 | Z20: =IF(Y20="y",$H$120,0) | AA20: =Z20*$C20 | AC20: =IF(AB20="y",$H$121,0) | AD20: =AC20*$C20 | AF20: =IF(AE20="y",$H$122,0) | AG20: =AF20*$C20 | AH20: =SUM(F20+I20+L20+O20+R20+U20+X20+AA20+AD20+AG20)
B21: Embeds - Titanium | C21: =40+20 | F21: =E21*$C21 | I21: =H21*$C21 | L21: =K21*$C21 | O21: =N21*$C21 | R21: =Q21*$C21 | U21: =T21*$C21 | X21: =W21*$C21 | AA21: =Z21*$C21 | AD21: =AC21*$C21 | AG21: =AF21*$C21 | AH21: =SUM(F21+I21+L21+O21+R21+U21+X21+AA21+AD21+AG21)
B22: Mounting holes (per hole cost) | C22: 6 | F22: =E22*$C22 | I22: =H22*$C22 | L22: =K22*$C22 | O22: =N22*$C22 | R22: =Q22*$C22 | U22: =T22*$C22 | X22: =W22*$C22 | AA22: =Z22*$C22 | AD22: =AC22*$C22 | AG22: =AF22*$C22 | AH22: =SUM(F22+I22+L22+O22+R22+U22+X22+AA22+AD22+AG22)
B23: Custom shapes | C23: 0.4 | F23: =E23*$C23 | I23: =H23*$C23 | L23: =K23*$C23 | O23: =N23*$C23 | R23: =Q23*$C23 | U23: =T23*$C23 | X23: =W23*$C23 | AA23: =Z23*$C23 | AH23: =SUM(F23+I23+L23+O23+R23+U23+X23+AA23+AD23+AG23)
B24: Round Glass | C24: 0.2 | F24: =IF(D24="Y",F9*$C$24,"") | I24: =IF(G24="Y",I9*$C$24,"") | L24: =IF(J24="Y",L9*$C$24,"") | O24: =IF(M24="Y",O9*$C$24,"") | R24: =IF(P24="Y",R9*$C$24,"") | U24: =IF(S24="Y",U9*$C$24,"") | X24: =IF(V24="Y",X9*$C$24,"") | AA24: =IF(Y24="Y",AA9*$C$24,"") | AH24: =SUM(F24+I24+L24+O24+R24+U24+X24+AA24+AD24+AG24)
B25: Misc Hardware | AH25: =SUM(F25+I25+L25+O25+R25+U25+X25+AA25+AD25+AG25)
B26: Railings
B27: How many sides need railings
C28: Width (Short Side) | F28: Width (Short Side) | I28: Width (Short Side) | L28: Width (Short Side) | O28: Width (Short Side) | R28: Width (Short Side) | U28: Width (Short Side) | X28: Width (Short Side) | AA28: Width (Short Side) | AD28: Width (Short Side) | AG28: Width (Short Side)
C29: Length (Long Side) | F29: Length (Long Side) | I29: Length (Long Side) | L29: Length (Long Side) | O29: Length (Long Side) | R29: Length (Long Side) | U29: Length (Long Side) | X29: Length (Long Side) | AA29: Length (Long Side) | AD29: Length (Long Side) | AG29: Length (Long Side)
B30: Mounting bracket for post | C30: 150 | E30: =IF(AND($D$28=0,$D$29=1),($K113+2),IF(AND($D$28=0,$D$29=2),(($K113*2)+4),IF(AND($D$28=1,$D$29=0),($L113+2),IF(AND($D$28=1,$D$29=1),($K113+$L113+3),IF(AND($D$28=1,$D$29=2),(($K113*2)+4+$L113),IF(AND($D$28=2,$D$29=0),(($L113*2)+4),IF(AND($D$28=2,$D$29=1),($K113+($L113*2)+4),IF(AND($D$28=2,$D$29=2),(($K113*2)+($L113*2)+4),"No Railings")))))))) | F30: =IF(D30="Y",$C$30*E30,"") | H30: =IF(AND($G$28=0,$G$29=1),($K114+2),IF(AND($G$28=0,$G$29=2),(($K114*2)+4),IF(AND($G$28=1,$G$29=0),($L114+2),IF(AND($G$28=1,$G$29=1),($K114+$L114+3),IF(AND($G$28=1,$G$29=2),(($K114*2)+4+$L114),IF(AND($G$28=2,$G$29=0),(($L114*2)+4),IF(AND($G$28=2,$G$29=1),($K114+($L114*2)+4),IF(AND($G$28=2,$G$29=2),(($K114*2)+($L114*2)+4),"No Railings")))))))) | I30: =IF(G30="Y",$C$30*H30,"") | K30: =IF(AND(J28=0,J29=1),($K115+2),IF(AND(J28=1,J29=0),($L115+2),IF(AND(J28=0,J29=2),(($K115*2)+4),IF(AND(J28=1,J29=0),($L115+2),IF(AND(J28=1,J29=1),($K115+2+$L115+1),IF(AND(J28=1,J29=2),(($K115*2)+4+$L115),IF(AND(J28=2,J29=0),(($L115*2)+4),IF(AND(J28=2,J29=1),($K115+2+($L115*2)+2),IF(AND(J28=2,J29=2),(($K115*2)+($L115*2)+4),"No Railings"))))))))) | L30: =IF(J30="Y",$C$30*K30,"") | N30: =IF(AND(M28=0,M29=1),($K116+2),IF(AND(M28=1,M29=0),($L116+2),IF(AND(M28=0,M29=2),(($K116*2)+4),IF(AND(M28=1,M29=0),($L116+2),IF(AND(M28=1,M29=1),($K116+2+$L116+1),IF(AND(M28=1,M29=2),(($K116*2)+4+$L116),IF(AND(M28=2,M29=0),(($L116*2)+4),IF(AND(M28=2,M29=1),($K116+2+($L116*2)+2),IF(AND(M28=2,M29=2),(($K116*2)+($L116*2)+4),"No Railings"))))))))) | O30: =IF(M30="Y",$C$30*N30,"") | Q30: =IF(AND(P28=0,P29=1),($K117+2),IF(AND(P28=1,P29=0),($L117+2),IF(AND(P28=0,P29=2),(($K117*2)+4),IF(AND(P28=1,P29=0),($L117+2),IF(AND(P28=1,P29=1),($K117+2+$L117+1),IF(AND(P28=1,P29=2),(($K117*2)+4+$L117),IF(AND(P28=2,P29=0),(($L117*2)+4),IF(AND(P28=2,P29=1),($K117+2+($L117*2)+2),IF(AND(P28=2,P29=2),(($K117*2)+($L117*2)+4),"No Railings"))))))))) | R30: =IF(P30="Y",$C$30*Q30,"") | T30: =IF(AND(S28=0,S29=1),($K118+2),IF(AND(S28=1,S29=0),($L118+2),IF(AND(S28=0,S29=2),(($K118*2)+4),IF(AND(S28=1,S29=0),($L118+2),IF(AND(S28=1,S29=1),($K118+2+$L118+1),IF(AND(S28=1,S29=2),(($K118*2)+4+$L118),IF(AND(S28=2,S29=0),(($L118*2)+4),IF(AND(S28=2,S29=1),($K118+2+($L118*2)+2),IF(AND(S28=2,S29=2),(($K118*2)+($L118*2)+4),"No Railings"))))))))) | U30: =IF(S30="Y",$C$30*T30,"") | W30: =IF(AND(V28=0,V29=1),($K119+2),IF(AND(V28=1,V29=0),($L119+2),IF(AND(V28=0,V29=2),(($K119*2)+4),IF(AND(V28=1,V29=0),($L119+2),IF(AND(V28=1,V29=1),($K119+2+$L119+1),IF(AND(V28=1,V29=2),(($K119*2)+4+$L119),IF(AND(V28=2,V29=0),(($L119*2)+4),IF(AND(V28=2,V29=1),($K119+2+($L119*2)+2),IF(AND(V28=2,V29=2),(($K119*2)+($L119*2)+4),"No Railings"))))))))) | X30: =IF(V30="Y",$C$30*W30,"") | Z30: =IF(AND(Y28=0,Y29=1),($K120+2),IF(AND(Y28=1,Y29=0),($L120+2),IF(AND(Y28=0,Y29=2),(($K120*2)+4),IF(AND(Y28=1,Y29=0),($L120+2),IF(AND(Y28=1,Y29=1),($K120+2+$L120+1),IF(AND(Y28=1,Y29=2),(($K120*2)+4+$L120),IF(AND(Y28=2,Y29=0),(($L120*2)+4),IF(AND(Y28=2,Y29=1),($K120+2+($L120*2)+2),IF(AND(Y28=2,Y29=2),(($K120*2)+($L120*2)+4),"No Railings"))))))))) | AA30: =IF(Y30="Y",$C$30*Z30,"") | AC30: =IF(AND(AB28=0,AB29=1),($K121+2),IF(AND(AB28=1,AB29=0),($L121+2),IF(AND(AB28=0,AB29=2),(($K121*2)+4),IF(AND(AB28=1,AB29=0),($L121+2),IF(AND(AB28=1,AB29=1),($K121+2+$L121+1),IF(AND(AB28=1,AB29=2),(($K121*2)+4+$L121),IF(AND(AB28=2,AB29=0),(($L121*2)+4),IF(AND(AB28=2,AB29=1),($K121+2+($L121*2)+2),IF(AND(AB28=2,AB29=2),(($K121*2)+($L121*2)+4),"No Railings"))))))))) | AD30: =IF(AB30="Y",$C$30*AC30,"") | AF30: =IF(AND(AE28=0,AE29=1),($K122+2),IF(AND(AE28=1,AE29=0),($L122+2),IF(AND(AE28=0,AE29=2),(($K122*2)+4),IF(AND(AE28=1,AE29=0),($L122+2),IF(AND(AE28=1,AE29=1),($K122+2+$L122+1),IF(AND(AE28=1,AE29=2),(($K122*2)+4+$L122),IF(AND(AE28=2,AE29=0),(($L122*2)+4),IF(AND(AE28=2,AE29=1),($K122+2+($L122*2)+2),IF(AND(AE28=2,AE29=2),(($K122*2)+($L122*2)+4),"No Railings"))))))))) | AG30: =IF(AE30="Y",$C$30*AF30,"") | AH30: =SUM(F30+I30+L30+O30+R30+U30+X30+AA30+AD30+AG30)
B31: Uprights | C31: 200 | E31: =IF(AND($D$28=0,$D$29=1),($K113+2),IF(AND($D$28=0,$D$29=2),(($K113*2)+4),IF(AND($D$28=1,$D$29=0),($L113+2),IF(AND($D$28=1,$D$29=1),($K113+$L113+3),IF(AND($D$28=1,$D$29=2),(($K113*2)+4+$L113),IF(AND($D$28=2,$D$29=0),(($L113*2)+4),IF(AND($D$28=2,$D$29=1),($K113+($L113*2)+4),IF(AND($D$28=2,$D$29=2),(($K113*2)+($L113*2)+4),"No Railings")))))))) | F31: =IF(D31="Y",$C$31*E31,"") | H31: =IF(AND(G28=0,G29=1),($K114+2),IF(AND(G28=1,G29=0),($L114+2),IF(AND(G28=0,G29=2),(($K114*2)+4),IF(AND(G28=1,G29=0),($L114+2),IF(AND(G28=1,G29=1),($K114+2+$L114+1),IF(AND(G28=1,G29=2),(($K114*2)+4+$L114),IF(AND(G28=2,G29=0),(($L114*2)+4),IF(AND(G28=2,G29=1),($K114+2+($L114*2)+2),IF(AND(G28=2,G29=2),(($K114*2)+($L114*2)+4),"No Railings"))))))))) | I31: =IF(G31="Y",$C$31*H31,"") | K31: =IF(AND(J28=0,J29=1),($K115+2),IF(AND(J28=1,J29=0),($L115+2),IF(AND(J28=0,J29=2),(($K115*2)+4),IF(AND(J28=1,J29=0),($L115+2),IF(AND(J28=1,J29=1),($K115+2+$L115+1),IF(AND(J28=1,J29=2),(($K115*2)+4+$L115),IF(AND(J28=2,J29=0),(($L115*2)+4),IF(AND(J28=2,J29=1),($K115+2+($L115*2)+2),IF(AND(J28=2,J29=2),(($K115*2)+($L115*2)+4),"No Railings"))))))))) | L31: =IF(J31="Y",$C$31*K31,"") | N31: =IF(AND(M28=0,M29=1),($K116+2),IF(AND(M28=1,M29=0),($L116+2),IF(AND(M28=0,M29=2),(($K116*2)+4),IF(AND(M28=1,M29=0),($L116+2),IF(AND(M28=1,M29=1),($K116+2+$L116+1),IF(AND(M28=1,M29=2),(($K116*2)+4+$L116),IF(AND(M28=2,M29=0),(($L116*2)+4),IF(AND(M28=2,M29=1),($K116+2+($L116*2)+2),IF(AND(M28=2,M29=2),(($K116*2)+($L116*2)+4),"No Railings"))))))))) | O31: =IF(M31="Y",$C$31*N31,"") | Q31: =IF(AND(P28=0,P29=1),($K117+2),IF(AND(P28=1,P29=0),($L117+2),IF(AND(P28=0,P29=2),(($K117*2)+4),IF(AND(P28=1,P29=0),($L117+2),IF(AND(P28=1,P29=1),($K117+2+$L117+1),IF(AND(P28=1,P29=2),(($K117*2)+4+$L117),IF(AND(P28=2,P29=0),(($L117*2)+4),IF(AND(P28=2,P29=1),($K117+2+($L117*2)+2),IF(AND(P28=2,P29=2),(($K117*2)+($L117*2)+4),"No Railings"))))))))) | R31: =IF(P31="Y",$C$31*Q31,"") | T31: =IF(AND(S28=0,S29=1),($K118+2),IF(AND(S28=1,S29=0),($L118+2),IF(AND(S28=0,S29=2),(($K118*2)+4),IF(AND(S28=1,S29=0),($L118+2),IF(AND(S28=1,S29=1),($K118+2+$L118+1),IF(AND(S28=1,S29=2),(($K118*2)+4+$L118),IF(AND(S28=2,S29=0),(($L118*2)+4),IF(AND(S28=2,S29=1),($K118+2+($L118*2)+2),IF(AND(S28=2,S29=2),(($K118*2)+($L118*2)+4),"No Railings"))))))))) | U31: =IF(S31="Y",$C$31*T31,"") | W31: =IF(AND(V28=0,V29=1),($K119+2),IF(AND(V28=1,V29=0),($L119+2),IF(AND(V28=0,V29=2),(($K119*2)+4),IF(AND(V28=1,V29=0),($L119+2),IF(AND(V28=1,V29=1),($K119+2+$L119+1),IF(AND(V28=1,V29=2),(($K119*2)+4+$L119),IF(AND(V28=2,V29=0),(($L119*2)+4),IF(AND(V28=2,V29=1),($K119+2+($L119*2)+2),IF(AND(V28=2,V29=2),(($K119*2)+($L119*2)+4),"No Railings"))))))))) | X31: =IF(V31="Y",$C$31*W31,"") | Z31: =IF(AND(Y28=0,Y29=1),($K120+2),IF(AND(Y28=1,Y29=0),($L120+2),IF(AND(Y28=0,Y29=2),(($K120*2)+4),IF(AND(Y28=1,Y29=0),($L120+2),IF(AND(Y28=1,Y29=1),($K120+2+$L120+1),IF(AND(Y28=1,Y29=2),(($K120*2)+4+$L120),IF(AND(Y28=2,Y29=0),(($L120*2)+4),IF(AND(Y28=2,Y29=1),($K120+2+($L120*2)+2),IF(AND(Y28=2,Y29=2),(($K120*2)+($L120*2)+4),"No Railings"))))))))) | AA31: =IF(Y31="Y",$C$31*Z31,"") | AC31: =IF(AND(AB28=0,AB29=1),($K121+2),IF(AND(AB28=1,AB29=0),($L121+2),IF(AND(AB28=0,AB29=2),(($K121*2)+4),IF(AND(AB28=1,AB29=0),($L121+2),IF(AND(AB28=1,AB29=1),($K121+2+$L121+1),IF(AND(AB28=1,AB29=2),(($K121*2)+4+$L121),IF(AND(AB28=2,AB29=0),(($L121*2)+4),IF(AND(AB28=2,AB29=1),($K121+2+($L121*2)+2),IF(AND(AB28=2,AB29=2),(($K121*2)+($L121*2)+4),"No Railings"))))))))) | AD31: =IF(AB31="Y",$C$31*AC31,"") | AF31: =IF(AND(AE28=0,AE29=1),($K122+2),IF(AND(AE28=1,AE29=0),($L122+2),IF(AND(AE28=0,AE29=2),(($K122*2)+4),IF(AND(AE28=1,AE29=0),($L122+2),IF(AND(AE28=1,AE29=1),($K122+2+$L122+1),IF(AND(AE28=1,AE29=2),(($K122*2)+4+$L122),IF(AND(AE28=2,AE29=0),(($L122*2)+4),IF(AND(AE28=2,AE29=1),($K122+2+($L122*2)+2),IF(AND(AE28=2,AE29=2),(($K122*2)+($L122*2)+4),"No Railings"))))))))) | AG31: =IF(AE31="Y",$C$31*AF31,"") | AH31: =SUM(F31+I31+L31+O31+R31+U31+X31+AA31+AD31+AG31)
B32: Cable Railing - per linear foot | C32: 55 | E32: =IF(AND($D$28=0,$D$29=1),($F$113/12),IF(AND($D$28=0,$D$29=2),(($F$113*2)/12),IF(AND($D$28=1,$D$29=0),($E$113/12),IF(AND($D$28=1,$D$29=1),(($E$113+$F$113)/12),IF(AND($D$28=1,$D$29=2),(($E$113+($F$113*2))/12),IF(AND($D$28=2,$D$29=0),(($E$113*2)/12),IF(AND($D$28=2,$D$29=1),((($E$113*2)+$F$113)/12),IF(AND($D$28=2,$D$29=2),((($E$113*2)+($F$113*2))/12),"No Railings")))))))) | F32: =IF(D32="Y",$C$32*E32,"") | H32: =IF(AND($G$28=0,$G$29=1),($F$114/12),IF(AND($G$28=0,$G$29=2),(($F$114*2)/12),IF(AND($G$28=1,$G$29=0),($E$114/12),IF(AND($G$28=1,$G$29=1),(($E$114+$F$114)/12),IF(AND($G$28=1,$G$29=2),(($E$114+($F$114*2))/12),IF(AND($G$28=2,$G$29=0),(($E$114*2)/12),IF(AND($G$28=2,$G$29=1),((($E$114*2)+$F$114)/12),IF(AND($G$28=2,$G$29=2),((($E$114*2)+($F$114*2))/12),"No Railings")))))))) | I32: =IF(G32="Y",$C$32*H32,"") | K32: =IF(AND($J$28=0,$J$29=1),($F$115/12),IF(AND($J$28=0,$J$29=2),(($F$115*2)/12),IF(AND($J$28=1,$J$29=0),($E$115/12),IF(AND($J$28=1,$J$29=1),(($E$115+$F$115)/12),IF(AND($J$28=1,$J$29=2),(($E$115+($F$115*2))/12),IF(AND($J$28=2,$J$29=0),(($E$115*2)/12),IF(AND($J$28=2,$J$29=1),((($E$115*2)+$F$115)/12),IF(AND($J$28=2,$J$29=2),((($E$115*2)+($F$115*2))/12),"No Railings")))))))) | L32: =IF(J32="Y",$C$32*K32,"") | N32: =IF(AND($M$28=0,$M$29=1),($F$116/12),IF(AND($M$28=0,$M$29=2),(($F$116*2)/12),IF(AND($M$28=1,$M$29=0),($E$116/12),IF(AND($M$28=1,$M$29=1),(($E$116+$F$116)/12),IF(AND($M$28=1,$M$29=2),(($E$116+($F$116*2))/12),IF(AND($M$28=2,$M$29=0),(($E$116*2)/12),IF(AND($M$28=2,$M$29=1),((($E$116*2)+$F$116)/12),IF(AND($M$28=2,$M$29=2),((($E$116*2)+($F$116*2))/12),"No Railings")))))))) | O32: =IF(M32="Y",$C$32*N32,"") | Q32: =IF(AND($P$28=0,$P$29=1),($F$117/12),IF(AND($P$28=0,$P$29=2),(($F$117*2)/12),IF(AND($P$28=1,$P$29=0),($E$117/12),IF(AND($P$28=1,$P$29=1),(($E$117+$F$117)/12),IF(AND($P$28=1,$P$29=2),(($E$117+($F$117*2))/12),IF(AND($P$28=2,$P$29=0),(($E$117*2)/12),IF(AND($P$28=2,$P$29=1),((($E$117*2)+$F$117)/12),IF(AND($P$28=2,$P$29=2),((($E$117*2)+($F$117*2))/12),"No Railings")))))))) | R32: =IF(P32="Y",$C$32*Q32,"") | T32: =IF(AND($S$28=0,$S$29=1),($F$118/12),IF(AND($S$28=0,$S$29=2),(($F$118*2)/12),IF(AND($S$28=1,$S$29=0),($E$118/12),IF(AND($S$28=1,$S$29=1),(($E$118+$F$118)/12),IF(AND($S$28=1,$S$29=2),(($E$118+($F$118*2))/12),IF(AND($S$28=2,$S$29=0),(($E$118*2)/12),IF(AND($S$28=2,$S$29=1),((($E$118*2)+$F$118)/12),IF(AND($S$28=2,$S$29=2),((($E$118*2)+($F$118*2))/12),"No Railings")))))))) | U32: =IF(S32="Y",$C$32*T32,"") | W32: =IF(AND($V$28=0,$V$29=1),($F$119/12),IF(AND($V$28=0,$V$29=2),(($F$119*2)/12),IF(AND($V$28=1,$V$29=0),($E$119/12),IF(AND($V$28=1,$V$29=1),(($E$119+$F$119)/12),IF(AND($V$28=1,$V$29=2),(($E$119+($F$119*2))/12),IF(AND($V$28=2,$V$29=0),(($E$119*2)/12),IF(AND($V$28=2,$V$29=1),((($E$119*2)+$F$119)/12),IF(AND($V$28=2,$V$29=2),((($E$119*2)+($F$119*2))/12),"No Railings")))))))) | X32: =IF(V32="Y",$C$32*W32,"") | Z32: =IF(AND($Y$28=0,$Y$29=1),($F$120/12),IF(AND($Y$28=0,$Y$29=2),(($F$120*2)/12),IF(AND($Y$28=1,$Y$29=0),($E$120/12),IF(AND($Y$28=1,$Y$29=1),(($E$120+$F$120)/12),IF(AND($Y$28=1,$Y$29=2),(($E$120+($F$120*2))/12),IF(AND($Y$28=2,$Y$29=0),(($E$120*2)/12),IF(AND($Y$28=2,$Y$29=1),((($E$120*2)+$F$120)/12),IF(AND($Y$28=2,$Y$29=2),((($E$120*2)+($F$120*2))/12),"No Railings")))))))) | AA32: =IF(Y32="Y",$C$32*Z32,"") | AC32: =IF(AND($AB$28=0,$AB$29=1),($F$121/12),IF(AND($AB$28=0,$AB$29=2),(($F$121*2)/12),IF(AND($AB$28=1,$AB$29=0),($E$121/12),IF(AND($AB$28=1,$AB$29=1),(($E$121+$F$121)/12),IF(AND($AB$28=1,$AB$29=2),(($E$121+($F$121*2))/12),IF(AND($AB$28=2,$AB$29=0),(($E$121*2)/12),IF(AND($AB$28=2,$AB$29=1),((($E$121*2)+$F$121)/12),IF(AND($AB$28=2,$AB$29=2),((($E$121*2)+($F$121*2))/12),"No Railings")))))))) | AD32: =IF(AB32="Y",$C$32*AC32,"") | AF32: =IF(AND($AE$28=0,$AE$29=1),($F$122/12),IF(AND($AE$28=0,$AE$29=2),(($F$122*2)/12),IF(AND($AE$28=1,$AE$29=0),($E$122/12),IF(AND($AE$28=1,$AE$29=1),(($E$122+$F$122)/12),IF(AND($AE$28=1,$AE$29=2),(($E$122+($F$122*2))/12),IF(AND($AE$28=2,$AE$29=0),(($E$122*2)/12),IF(AND($AE$28=2,$AE$29=1),((($E$122*2)+$F$122)/12),IF(AND($AE$28=2,$AE$29=2),((($E$122*2)+($F$122*2))/12),"No Railings")))))))) | AG32: =IF(AE32="Y",$C$32*AF32,"") | AH32: =SUM(F32+I32+L32+O32+R32+U32+X32+AA32+AD32+AG32)
B33: Glass Railing - 42" High - per linear foot | C33: 91 | E33: =IF(AND($D$28=0,$D$29=1),($F$113/12),IF(AND($D$28=0,$D$29=2),(($F$113*2)/12),IF(AND($D$28=1,$D$29=0),($E$113/12),IF(AND($D$28=1,$D$29=1),(($E$113+$F$113)/12),IF(AND($D$28=1,$D$29=2),(($E$113+($F$113*2))/12),IF(AND($D$28=2,$D$29=0),(($E$113*2)/12),IF(AND($D$28=2,$D$29=1),((($E$113*2)+$F$113)/12),IF(AND($D$28=2,$D$29=2),((($E$113*2)+($F$113*2))/12),"No Railings")))))))) | F33: =IF(D33="Y",$C$33*E33,"") | H33: =IF(AND($G$28=0,$G$29=1),($F$114/12),IF(AND($G$28=0,$G$29=2),(($F$114*2)/12),IF(AND($G$28=1,$G$29=0),($E$114/12),IF(AND($G$28=1,$G$29=1),(($E$114+$F$114)/12),IF(AND($G$28=1,$G$29=2),(($E$114+($F$114*2))/12),IF(AND($G$28=2,$G$29=0),(($E$114*2)/12),IF(AND($G$28=2,$G$29=1),((($E$114*2)+$F$114)/12),IF(AND($G$28=2,$G$29=2),((($E$114*2)+($F$114*2))/12),"No Railings")))))))) | I33: =IF(G33="Y",$C$33*H33,"") | K33: =IF(AND($J$28=0,$J$29=1),($F$115/12),IF(AND($J$28=0,$J$29=2),(($F$115*2)/12),IF(AND($J$28=1,$J$29=0),($E$115/12),IF(AND($J$28=1,$J$29=1),(($E$115+$F$115)/12),IF(AND($J$28=1,$J$29=2),(($E$115+($F$115*2))/12),IF(AND($J$28=2,$J$29=0),(($E$115*2)/12),IF(AND($J$28=2,$J$29=1),((($E$115*2)+$F$115)/12),IF(AND($J$28=2,$J$29=2),((($E$115*2)+($F$115*2))/12),"No Railings")))))))) | L33: =IF(J33="Y",$C$33*K33,"") | N33: =IF(AND($M$28=0,$M$29=1),($F$116/12),IF(AND($M$28=0,$M$29=2),(($F$116*2)/12),IF(AND($M$28=1,$M$29=0),($E$116/12),IF(AND($M$28=1,$M$29=1),(($E$116+$F$116)/12),IF(AND($M$28=1,$M$29=2),(($E$116+($F$116*2))/12),IF(AND($M$28=2,$M$29=0),(($E$116*2)/12),IF(AND($M$28=2,$M$29=1),((($E$116*2)+$F$116)/12),IF(AND($M$28=2,$M$29=2),((($E$116*2)+($F$116*2))/12),"No Railings")))))))) | O33: =IF(M33="Y",$C$33*N33,"") | Q33: =IF(AND($P$28=0,$P$29=1),($F$117/12),IF(AND($P$28=0,$P$29=2),(($F$117*2)/12),IF(AND($P$28=1,$P$29=0),($E$117/12),IF(AND($P$28=1,$P$29=1),(($E$117+$F$117)/12),IF(AND($P$28=1,$P$29=2),(($E$117+($F$117*2))/12),IF(AND($P$28=2,$P$29=0),(($E$117*2)/12),IF(AND($P$28=2,$P$29=1),((($E$117*2)+$F$117)/12),IF(AND($P$28=2,$P$29=2),((($E$117*2)+($F$117*2))/12),"No Railings")))))))) | R33: =IF(P33="Y",$C$33*Q33,"") | T33: =IF(AND($S$28=0,$S$29=1),($F$118/12),IF(AND($S$28=0,$S$29=2),(($F$118*2)/12),IF(AND($S$28=1,$S$29=0),($E$118/12),IF(AND($S$28=1,$S$29=1),(($E$118+$F$118)/12),IF(AND($S$28=1,$S$29=2),(($E$118+($F$118*2))/12),IF(AND($S$28=2,$S$29=0),(($E$118*2)/12),IF(AND($S$28=2,$S$29=1),((($E$118*2)+$F$118)/12),IF(AND($S$28=2,$S$29=2),((($E$118*2)+($F$118*2))/12),"No Railings")))))))) | U33: =IF(S33="Y",$C$33*T33,"") | W33: =IF(AND($V$28=0,$V$29=1),($F$119/12),IF(AND($V$28=0,$V$29=2),(($F$119*2)/12),IF(AND($V$28=1,$V$29=0),($E$119/12),IF(AND($V$28=1,$V$29=1),(($E$119+$F$119)/12),IF(AND($V$28=1,$V$29=2),(($E$119+($F$119*2))/12),IF(AND($V$28=2,$V$29=0),(($E$119*2)/12),IF(AND($V$28=2,$V$29=1),((($E$119*2)+$F$119)/12),IF(AND($V$28=2,$V$29=2),((($E$119*2)+($F$119*2))/12),"No Railings")))))))) | X33: =IF(V33="Y",$C$33*W33,"") | Z33: =IF(AND($Y$28=0,$Y$29=1),($F$120/12),IF(AND($Y$28=0,$Y$29=2),(($F$120*2)/12),IF(AND($Y$28=1,$Y$29=0),($E$120/12),IF(AND($Y$28=1,$Y$29=1),(($E$120+$F$120)/12),IF(AND($Y$28=1,$Y$29=2),(($E$120+($F$120*2))/12),IF(AND($Y$28=2,$Y$29=0),(($E$120*2)/12),IF(AND($Y$28=2,$Y$29=1),((($E$120*2)+$F$120)/12),IF(AND($Y$28=2,$Y$29=2),((($E$120*2)+($F$120*2))/12),"No Railings")))))))) | AA33: =IF(Y33="Y",$C$33*Z33,"") | AC33: =IF(AND($AB$28=0,$AB$29=1),($F$121/12),IF(AND($AB$28=0,$AB$29=2),(($F$121*2)/12),IF(AND($AB$28=1,$AB$29=0),($E$121/12),IF(AND($AB$28=1,$AB$29=1),(($E$121+$F$121)/12),IF(AND($AB$28=1,$AB$29=2),(($E$121+($F$121*2))/12),IF(AND($AB$28=2,$AB$29=0),(($E$121*2)/12),IF(AND($AB$28=2,$AB$29=1),((($E$121*2)+$F$121)/12),IF(AND($AB$28=2,$AB$29=2),((($E$121*2)+($F$121*2))/12),"No Railings")))))))) | AD33: =IF(AB33="Y",$C$33*AC33,"") | AF33: =IF(AND($AE$28=0,$AE$29=1),($F$122/12),IF(AND($AE$28=0,$AE$29=2),(($F$122*2)/12),IF(AND($AE$28=1,$AE$29=0),($E$122/12),IF(AND($AE$28=1,$AE$29=1),(($E$122+$F$122)/12),IF(AND($AE$28=1,$AE$29=2),(($E$122+($F$122*2))/12),IF(AND($AE$28=2,$AE$29=0),(($E$122*2)/12),IF(AND($AE$28=2,$AE$29=1),((($E$122*2)+$F$122)/12),IF(AND($AE$28=2,$AE$29=2),((($E$122*2)+($F$122*2))/12),"No Railings")))))))) | AG33: =IF(AE33="Y",$C$33*AF33,"") | AH33: =SUM(F33+I33+L33+O33+R33+U33+X33+AA33+AD33+AG33)
B34: Top Rail - per linear foot | C34: 120 | E34: =IF(AND($D$28=0,$D$29=1),($F$113/12),IF(AND($D$28=0,$D$29=2),(($F$113*2)/12),IF(AND($D$28=1,$D$29=0),($E$113/12),IF(AND($D$28=1,$D$29=1),(($E$113+$F$113)/12),IF(AND($D$28=1,$D$29=2),(($E$113+($F$113*2))/12),IF(AND($D$28=2,$D$29=0),(($E$113*2)/12),IF(AND($D$28=2,$D$29=1),((($E$113*2)+$F$113)/12),IF(AND($D$28=2,$D$29=2),((($E$113*2)+($F$113*2))/12),"No Railings")))))))) | F34: =IF(D34="Y",$C$34*E34,"") | H34: =IF(AND($G$28=0,$G$29=1),($F$114/12),IF(AND($G$28=0,$G$29=2),(($F$114*2)/12),IF(AND($G$28=1,$G$29=0),($E$114/12),IF(AND($G$28=1,$G$29=1),(($E$114+$F$114)/12),IF(AND($G$28=1,$G$29=2),(($E$114+($F$114*2))/12),IF(AND($G$28=2,$G$29=0),(($E$114*2)/12),IF(AND($G$28=2,$G$29=1),((($E$114*2)+$F$114)/12),IF(AND($G$28=2,$G$29=2),((($E$114*2)+($F$114*2))/12),"No Railings")))))))) | I34: =IF(G34="Y",$C$34*H34,"") | K34: =IF(AND($J$28=0,$J$29=1),($F$115/12),IF(AND($J$28=0,$J$29=2),(($F$115*2)/12),IF(AND($J$28=1,$J$29=0),($E$115/12),IF(AND($J$28=1,$J$29=1),(($E$115+$F$115)/12),IF(AND($J$28=1,$J$29=2),(($E$115+($F$115*2))/12),IF(AND($J$28=2,$J$29=0),(($E$115*2)/12),IF(AND($J$28=2,$J$29=1),((($E$115*2)+$F$115)/12),IF(AND($J$28=2,$J$29=2),((($E$115*2)+($F$115*2))/12),"No Railings")))))))) | L34: =IF(J34="Y",$C$34*K34,"") | N34: =IF(AND($M$28=0,$M$29=1),($F$116/12),IF(AND($M$28=0,$M$29=2),(($F$116*2)/12),IF(AND($M$28=1,$M$29=0),($E$116/12),IF(AND($M$28=1,$M$29=1),(($E$116+$F$116)/12),IF(AND($M$28=1,$M$29=2),(($E$116+($F$116*2))/12),IF(AND($M$28=2,$M$29=0),(($E$116*2)/12),IF(AND($M$28=2,$M$29=1),((($E$116*2)+$F$116)/12),IF(AND($M$28=2,$M$29=2),((($E$116*2)+($F$116*2))/12),"No Railings")))))))) | O34: =IF(M34="Y",$C$34*N34,"") | Q34: =IF(AND($P$28=0,$P$29=1),($F$117/12),IF(AND($P$28=0,$P$29=2),(($F$117*2)/12),IF(AND($P$28=1,$P$29=0),($E$117/12),IF(AND($P$28=1,$P$29=1),(($E$117+$F$117)/12),IF(AND($P$28=1,$P$29=2),(($E$117+($F$117*2))/12),IF(AND($P$28=2,$P$29=0),(($E$117*2)/12),IF(AND($P$28=2,$P$29=1),((($E$117*2)+$F$117)/12),IF(AND($P$28=2,$P$29=2),((($E$117*2)+($F$117*2))/12),"No Railings")))))))) | R34: =IF(P34="Y",$C$34*Q34,"") | T34: =IF(AND($S$28=0,$S$29=1),($F$118/12),IF(AND($S$28=0,$S$29=2),(($F$118*2)/12),IF(AND($S$28=1,$S$29=0),($E$118/12),IF(AND($S$28=1,$S$29=1),(($E$118+$F$118)/12),IF(AND($S$28=1,$S$29=2),(($E$118+($F$118*2))/12),IF(AND($S$28=2,$S$29=0),(($E$118*2)/12),IF(AND($S$28=2,$S$29=1),((($E$118*2)+$F$118)/12),IF(AND($S$28=2,$S$29=2),((($E$118*2)+($F$118*2))/12),"No Railings")))))))) | U34: =IF(S34="Y",$C$34*T34,"") | W34: =IF(AND($V$28=0,$V$29=1),($F$119/12),IF(AND($V$28=0,$V$29=2),(($F$119*2)/12),IF(AND($V$28=1,$V$29=0),($E$119/12),IF(AND($V$28=1,$V$29=1),(($E$119+$F$119)/12),IF(AND($V$28=1,$V$29=2),(($E$119+($F$119*2))/12),IF(AND($V$28=2,$V$29=0),(($E$119*2)/12),IF(AND($V$28=2,$V$29=1),((($E$119*2)+$F$119)/12),IF(AND($V$28=2,$V$29=2),((($E$119*2)+($F$119*2))/12),"No Railings")))))))) | X34: =IF(V34="Y",$C$34*W34,"") | Z34: =IF(AND($Y$28=0,$Y$29=1),($F$120/12),IF(AND($Y$28=0,$Y$29=2),(($F$120*2)/12),IF(AND($Y$28=1,$Y$29=0),($E$120/12),IF(AND($Y$28=1,$Y$29=1),(($E$120+$F$120)/12),IF(AND($Y$28=1,$Y$29=2),(($E$120+($F$120*2))/12),IF(AND($Y$28=2,$Y$29=0),(($E$120*2)/12),IF(AND($Y$28=2,$Y$29=1),((($E$120*2)+$F$120)/12),IF(AND($Y$28=2,$Y$29=2),((($E$120*2)+($F$120*2))/12),"No Railings")))))))) | AA34: =IF(Y34="Y",$C$34*Z34,"") | AC34: =IF(AND($AB$28=0,$AB$29=1),($F$121/12),IF(AND($AB$28=0,$AB$29=2),(($F$121*2)/12),IF(AND($AB$28=1,$AB$29=0),($E$121/12),IF(AND($AB$28=1,$AB$29=1),(($E$121+$F$121)/12),IF(AND($AB$28=1,$AB$29=2),(($E$121+($F$121*2))/12),IF(AND($AB$28=2,$AB$29=0),(($E$121*2)/12),IF(AND($AB$28=2,$AB$29=1),((($E$121*2)+$F$121)/12),IF(AND($AB$28=2,$AB$29=2),((($E$121*2)+($F$121*2))/12),"No Railings")))))))) | AD34: =IF(AB34="Y",$C$34*AC34,"") | AF34: =IF(AND($AE$28=0,$AE$29=1),($F$122/12),IF(AND($AE$28=0,$AE$29=2),(($F$122*2)/12),IF(AND($AE$28=1,$AE$29=0),($E$122/12),IF(AND($AE$28=1,$AE$29=1),(($E$122+$F$122)/12),IF(AND($AE$28=1,$AE$29=2),(($E$122+($F$122*2))/12),IF(AND($AE$28=2,$AE$29=0),(($E$122*2)/12),IF(AND($AE$28=2,$AE$29=1),((($E$122*2)+$F$122)/12),IF(AND($AE$28=2,$AE$29=2),((($E$122*2)+($F$122*2))/12),"No Railings")))))))) | AG34: =IF(AE34="Y",$C$34*AF34,"") | AH34: =SUM(F34+I34+L34+O34+R34+U34+X34+AA34+AD34+AG34)
B35: Framing - Linear Feet
B36: Perimeter
B37: Series 1000 Pedestal thermally broken | C37: ='Bonnell - Glass Pricing'!H14 | E37: =IF(D37="y",$I$113,0) | F37: =E37*$C37 | H37: =IF(G37="y",$I$114,0) | I37: =H37*$C37 | K37: =IF(J37="y",$I$115,0) | L37: =K37*$C37 | N37: =IF(M37="y",$I$116,0) | O37: =N37*$C37 | Q37: =IF(P37="y",$I$117,0) | R37: =Q37*$C37 | T37: =IF(S37="y",$I$118,0) | U37: =T37*$C37 | W37: =IF(V37="y",$I$119,0) | X37: =W37*$C37 | Z37: =IF(Y37="y",$I$120,0) | AA37: =Z37*$C37 | AC37: =IF(AB37="y",$I$121,0) | AD37: =AC37*$C37 | AF37: =IF(AE37="y",$I$122,0) | AG37: =AF37*$C37 | AH37: =SUM(F37+I37+L37+O37+R37+U37+X37+AA37+AD37+AG37)
B38: Series 1000 Recessed thermally broken | C38: ='Bonnell - Glass Pricing'!H15 | E38: =IF(D38="y",$I$113,0) | F38: =E38*$C38 | H38: =IF(G38="y",$I$114,0) | I38: =H38*$C38 | K38: =IF(J38="y",$I$115,0) | L38: =K38*$C38 | N38: =IF(M38="y",$I$116,0) | O38: =N38*$C38 | Q38: =IF(P38="y",$I$117,0) | R38: =Q38*$C38 | T38: =IF(S38="y",$I$118,0) | U38: =T38*$C38 | W38: =IF(V38="y",$I$119,0) | X38: =W38*$C38 | Z38: =IF(Y38="y",$I$120,0) | AA38: =Z38*$C38 | AC38: =IF(AB38="y",$I$121,0) | AD38: =AC38*$C38 | AF38: =IF(AE38="y",$I$122,0) | AG38: =AF38*$C38 | AH38: =SUM(F38+I38+L38+O38+R38+U38+X38+AA38+AD38+AG38)
B39: Perimeter non thermally broken | C39: ='Bonnell - Glass Pricing'!H16 | E39: =IF(D39="y",$I$113,0) | F39: =E39*$C39 | H39: =IF(G39="y",$I$114,0) | I39: =H39*$C39 | K39: =IF(J39="y",$I$115,0) | L39: =K39*$C39 | N39: =IF(M39="y",$I$116,0) | O39: =N39*$C39 | Q39: =IF(P39="y",$I$117,0) | R39: =Q39*$C39 | T39: =IF(S39="y",$I$118,0) | U39: =T39*$C39 | W39: =IF(V39="y",$I$119,0) | X39: =W39*$C39 | Z39: =IF(Y39="y",$I$120,0) | AA39: =Z39*$C39 | AC39: =IF(AB39="y",$I$121,0) | AD39: =AC39*$C39 | AF39: =IF(AE39="y",$I$122,0) | AG39: =AF39*$C39 | AH39: =SUM(F39+I39+L39+O39+R39+U39+X39+AA39+AD39+AG39)
B40: Series 2000 Pedestal | C40: ='Bonnell - Glass Pricing'!H46 | E40: =IF(D40="y",$I$113,0) | F40: =E40*$C40 | H40: =IF(G40="y",$I$114,0) | I40: =H40*$C40 | K40: =IF(J40="y",$I$115,0) | L40: =K40*$C40 | N40: =IF(M40="y",$I$116,0) | O40: =N40*$C40 | Q40: =IF(P40="y",$I$117,0) | R40: =Q40*$C40 | T40: =IF(S40="y",$I$118,0) | U40: =T40*$C40 | W40: =IF(V40="y",$I$119,0) | X40: =W40*$C40 | Z40: =IF(Y40="y",$I$120,0) | AA40: =Z40*$C40 | AC40: =IF(AB40="y",$I$121,0) | AD40: =AC40*$C40 | AF40: =IF(AE40="y",$I$122,0) | AG40: =AF40*$C40 | AH40: =SUM(F40+I40+L40+O40+R40+U40+X40+AA40+AD40+AG40)
B41: Series 2000 Recessed | C41: ='Bonnell - Glass Pricing'!H47 | E41: =IF(D41="y",$I$113,0) | F41: =E41*$C41 | H41: =IF(G41="y",$I$114,0) | I41: =H41*$C41 | K41: =IF(J41="y",$I$115,0) | L41: =K41*$C41 | N41: =IF(M41="y",$I$116,0) | O41: =N41*$C41 | Q41: =IF(P41="y",$I$117,0) | R41: =Q41*$C41 | T41: =IF(S41="y",$I$118,0) | U41: =T41*$C41 | W41: =IF(V41="y",$I$119,0) | X41: =W41*$C41 | Z41: =IF(Y41="y",$I$120,0) | AA41: =Z41*$C41 | AC41: =IF(AB41="y",$I$121,0) | AD41: =AC41*$C41 | AF41: =IF(AE41="y",$I$122,0) | AG41: =AF41*$C41 | AH41: =SUM(F41+I41+L41+O41+R41+U41+X41+AA41+AD41+AG41)
B42: Series 2000 with plate | C42: ='Bonnell - Glass Pricing'!H48 | E42: =IF(D42="y",$I$113,0) | F42: =E42*$C42 | H42: =IF(G42="y",$I$114,0) | I42: =H42*$C42 | K42: =IF(J42="y",$I$115,0) | L42: =K42*$C42 | N42: =IF(M42="y",$I$116,0) | O42: =N42*$C42 | Q42: =IF(P42="y",$I$117,0) | R42: =Q42*$C42 | T42: =IF(S42="y",$I$118,0) | U42: =T42*$C42 | W42: =IF(V42="y",$I$119,0) | X42: =W42*$C42 | Z42: =IF(Y42="y",$I$120,0) | AA42: =Z42*$C42 | AC42: =IF(AB42="y",$I$121,0) | AD42: =AC42*$C42 | AF42: =IF(AE42="y",$I$122,0) | AG42: =AF42*$C42 | AH42: =SUM(F42+I42+L42+O42+R42+U42+X42+AA42+AD42+AG42)
B43: Series 2000 non-walkable | E43: =IF(D43="y",$I$113,0) | F43: =E43*$C43 | H43: =IF(G43="y",$I$114,0) | I43: =H43*$C43 | K43: =IF(J43="y",$I$115,0) | L43: =K43*$C43 | N43: =IF(M43="y",$I$116,0) | O43: =N43*$C43 | Q43: =IF(P43="y",$I$117,0) | R43: =Q43*$C43 | T43: =IF(S43="y",$I$118,0) | U43: =T43*$C43 | W43: =IF(V43="y",$I$119,0) | X43: =W43*$C43 | Z43: =IF(Y43="y",$I$120,0) | AA43: =Z43*$C43 | AC43: =IF(AB43="y",$I$121,0) | AD43: =AC43*$C43 | AF43: =IF(AE43="y",$I$122,0) | AG43: =AF43*$C43 | AH43: =SUM(F43+I43+L43+O43+R43+U43+X43+AA43+AD43+AG43)
B44: Deck perimeter | C44: ='Bonnell - Glass Pricing'!H20 | E44: =IF(D44="y",$I$113,0) | F44: =E44*$C44 | H44: =IF(G44="y",$I$114,0) | I44: =H44*$C44 | K44: =IF(J44="y",$I$115,0) | L44: =K44*$C44 | N44: =IF(M44="y",$I$116,0) | O44: =N44*$C44 | Q44: =IF(P44="y",$I$117,0) | R44: =Q44*$C44 | T44: =IF(S44="y",$I$118,0) | U44: =T44*$C44 | W44: =IF(V44="y",$I$119,0) | X44: =W44*$C44 | Z44: =IF(Y44="y",$I$120,0) | AA44: =Z44*$C44 | AC44: =IF(AB44="y",$I$121,0) | AD44: =AC44*$C44 | AF44: =IF(AE44="y",$I$122,0) | AG44: =AF44*$C44 | AH44: =SUM(F44+I44+L44+O44+R44+U44+X44+AA44+AD44+AG44)
B45: Econoframe - lengths | C45: ='Bonnell - Glass Pricing'!I6 | E45: =IF(D45="y",$I$113,0) | F45: =E45*$C$45 | H45: =IF(G45="y",$I$114,0) | I45: =H45*$C$45 | K45: =IF(J45="y",$I$115,0) | L45: =K45*$C$45 | N45: =IF(M45="y",$I$116,0) | O45: =N45*$C$45 | Q45: =IF(P45="y",$I$117,0) | R45: =Q45*$C$45 | T45: =IF(S45="y",$I$118,0) | U45: =T45*$C$45 | W45: =IF(V45="y",$I$119,0) | X45: =W45*$C$45 | Z45: =IF(Y45="y",$I$120,0) | AA45: =Z45*$C$45 | AC45: =IF(AB45="y",$I$121,0) | AD45: =AC45*$C45 | AF45: =IF(AE45="y",$I$122,0) | AG45: =AF45*$C45 | AH45: =SUM(F45+I45+L45+O45+R45+U45+X45+AA45+AD45+AG45)
B46: Round Frame 42" | C46: 650 | F46: =E46*$C$46 | I46: =H46*$C$46 | L46: =K46*$C$46 | O46: =N46*$C$46 | R46: =Q46*$C$46 | U46: =T46*$C$46 | X46: =W46*$C$46 | AA46: =Z46*$C$46 | AD46: =AC46*$C$46 | AG46: =AF46*$C$46 | AH46: =SUM(F46+I46+L46+O46+R46+U46+X46+AA46+AD46+AG46)
B47: 2" Horizontal cap - Series 1000 | C47: ='Bonnell - Glass Pricing'!I31 | E47: =IF(D47="y",$I$113,0) | F47: =E47*$C$45 | H47: =IF(G47="y",$I$114,0) | I47: =H47*$C$45 | K47: =IF(J47="y",$I$115,0) | L47: =K47*$C$45 | N47: =IF(M47="y",$I$116,0) | O47: =N47*$C$45 | Q47: =IF(P47="y",$I$117,0) | R47: =Q47*$C$45 | T47: =IF(S47="y",$I$118,0) | U47: =T47*$C$45 | W47: =IF(V47="y",$I$119,0) | X47: =W47*$C$45 | Z47: =IF(Y47="y",$I$120,0) | AA47: =Z47*$C$45 | AC47: =IF(AB47="y",$I$121,0) | AD47: =AC47*$C47 | AF47: =IF(AE47="y",$I$122,0) | AG47: =AF47*$C47 | AH47: =SUM(F47+I47+L47+O47+R47+U47+X47+AA47+AD47+AG47)
B48: 3' Vertical cap - Series 1000 | C48: ='Bonnell - Glass Pricing'!I32 | E48: =IF(D48="y",$I$113,0) | F48: =E48*$C$45 | H48: =IF(G48="y",$I$114,0) | I48: =H48*$C$45 | K48: =IF(J48="y",$I$115,0) | L48: =K48*$C$45 | N48: =IF(M48="y",$I$116,0) | O48: =N48*$C$45 | Q48: =IF(P48="y",$I$117,0) | R48: =Q48*$C$45 | T48: =IF(S48="y",$I$118,0) | U48: =T48*$C$45 | W48: =IF(V48="y",$I$119,0) | X48: =W48*$C$45 | Z48: =IF(Y48="y",$I$120,0) | AA48: =Z48*$C$45 | AC48: =IF(AB48="y",$I$121,0) | AD48: =AC48*$C48 | AF48: =IF(AE48="y",$I$122,0) | AG48: =AF48*$C48 | AH48: =SUM(F48+I48+L48+O48+R48+U48+X48+AA48+AD48+AG48)
B49: Custom fab | AH49: =SUM(F49+I49+L49+O49+R49+U49+X49+AA49+AD49+AG49)
B50: Cross Beam
B51: Series 1000 T - Section thermally Broken | C51: ='Bonnell - Glass Pricing'!H11 | E51: =IF(D51="y",$N$113,0)/12 | F51: =E51*$C51 | H51: =IF(G51="y",$N$114,0)/12 | I51: =H51*$C51 | K51: =IF(J51="y",$N$115,0)/12 | L51: =K51*$C51 | N51: =IF(M51="y",$N$116,0)/12 | O51: =N51*$C51 | Q51: =IF(P51="y",$N$117,0)/12 | R51: =Q51*$C51 | T51: =IF(S51="y",$N$118,0)/12 | U51: =T51*$C51 | W51: =IF(V51="y",$N$119,0)/12 | X51: =W51*$C51 | Z51: =IF(Y51="y",$N$120,0)/12 | AA51: =Z51*$C51 | AC51: =IF(AB51="y",$N$121,0)/12 | AD51: =AC51*$C51 | AF51: =IF(AE51="y",$N$122,0)/12 | AG51: =AF51*$C51 | AH51: =SUM(F51+I51+L51+O51+R51+U51+X51+AA51+AD51+AG51)
B52: Series 1000 I - Beam thermally broken | C52: ='Bonnell - Glass Pricing'!H13 | E52: =IF(D52="y",$N$113,0)/12 | F52: =E52*$C52 | H52: =IF(G52="y",$N$114,0)/12 | I52: =H52*$C52 | K52: =IF(J52="y",$N$115,0)/12 | L52: =K52*$C52 | N52: =IF(M52="y",$N$116,0)/12 | O52: =N52*$C52 | Q52: =IF(P52="y",$N$117,0)/12 | R52: =Q52*$C52 | T52: =IF(S52="y",$N$118,0)/12 | U52: =T52*$C52 | W52: =IF(V52="y",$N$119,0)/12 | X52: =W52*$C52 | Z52: =IF(Y52="y",$N$120,0)/12 | AA52: =Z52*$C52 | AC52: =IF(AB52="y",$N$121,0)/12 | AD52: =AC52*$C52 | AF52: =IF(AE52="y",$N$122,0)/12 | AG52: =AF52*$C52 | AH52: =SUM(F52+I52+L52+O52+R52+U52+X52+AA52+AD52+AG52)
B53: Series 1000 T - Section | C53: ='Bonnell - Glass Pricing'!H10 | E53: =IF(D53="y",$N$113,0)/12 | F53: =E53*$C53 | H53: =IF(G53="y",$N$114,0)/12 | I53: =H53*$C53 | K53: =IF(J53="y",$N$115,0)/12 | L53: =K53*$C53 | N53: =IF(M53="y",$N$116,0)/12 | O53: =N53*$C53 | Q53: =IF(P53="y",$N$117,0)/12 | R53: =Q53*$C53 | T53: =IF(S53="y",$N$118,0)/12 | U53: =T53*$C53 | W53: =IF(V53="y",$N$119,0)/12 | X53: =W53*$C53 | Z53: =IF(Y53="y",$N$120,0)/12 | AA53: =Z53*$C53 | AC53: =IF(AB53="y",$N$121,0)/12 | AD53: =AC53*$C53 | AF53: =IF(AE53="y",$N$122,0)/12 | AG53: =AF53*$C53 | AH53: =SUM(F53+I53+L53+O53+R53+U53+X53+AA53+AD53+AG53)
B54: Series 1000 I - Beam | C54: ='Bonnell - Glass Pricing'!H12 | E54: =IF(D54="y",$N$113,0)/12 | F54: =E54*$C54 | H54: =IF(G54="y",$N$114,0)/12 | I54: =H54*$C54 | K54: =IF(J54="y",$N$115,0)/12 | L54: =K54*$C54 | N54: =IF(M54="y",$N$116,0)/12 | O54: =N54*$C54 | Q54: =IF(P54="y",$N$117,0)/12 | R54: =Q54*$C54 | T54: =IF(S54="y",$N$118,0)/12 | U54: =T54*$C54 | W54: =IF(V54="y",$N$119,0)/12 | X54: =W54*$C54 | Z54: =IF(Y54="y",$N$120,0)/12 | AA54: =Z54*$C54 | AC54: =IF(AB54="y",$N$121,0)/12 | AD54: =AC54*$C54 | AF54: =IF(AE54="y",$N$122,0)/12 | AG54: =AF54*$C54 | AH54: =SUM(F54+I54+L54+O54+R54+U54+X54+AA54+AD54+AG54)
B55: Series 2000 T section thermally broken | E55: =IF(D55="y",$N$113,0)/12 | F55: =E55*$C55 | H55: =IF(G55="y",$N$114,0)/12 | I55: =H55*$C55 | K55: =IF(J55="y",$N$115,0)/12 | L55: =K55*$C55 | N55: =IF(M55="y",$N$116,0)/12 | O55: =N55*$C55 | Q55: =IF(P55="y",$N$117,0)/12 | R55: =Q55*$C55 | T55: =IF(S55="y",$N$118,0)/12 | U55: =T55*$C55 | W55: =IF(V55="y",$N$119,0)/12 | X55: =W55*$C55 | Z55: =IF(Y55="y",$N$120,0)/12 | AA55: =Z55*$C55 | AC55: =IF(AB55="y",$N$121,0)/12 | AD55: =AC55*$C55 | AF55: =IF(AE55="y",$N$122,0)/12 | AG55: =AF55*$C55 | AH55: =SUM(F55+I55+L55+O55+R55+U55+X55+AA55+AD55+AG55)
B56: Series 2000 I beam thermally broken | C56: 41 | E56: =IF(D56="y",$N$113,0)/12 | F56: =E56*$C56 | H56: =IF(G56="y",$N$114,0)/12 | I56: =H56*$C56 | K56: =IF(J56="y",$N$115,0)/12 | L56: =K56*$C56 | N56: =IF(M56="y",$N$116,0)/12 | O56: =N56*$C56 | Q56: =IF(P56="y",$N$117,0)/12 | R56: =Q56*$C56 | T56: =IF(S56="y",$N$118,0)/12 | U56: =T56*$C56 | W56: =IF(V56="y",$N$119,0)/12 | X56: =W56*$C56 | Z56: =IF(Y56="y",$N$120,0)/12 | AA56: =Z56*$C56 | AC56: =IF(AB56="y",$N$121,0)/12 | AD56: =AC56*$C56 | AF56: =IF(AE56="y",$N$122,0)/12 | AG56: =AF56*$C56 | AH56: =SUM(F56+I56+L56+O56+R56+U56+X56+AA56+AD56+AG56)
B57: Econoframe 2.5 | C57: ='Bonnell - Glass Pricing'!I7 | E57: =IF(D57="y",$N$113,0)/12 | F57: =E57*$C$57 | H57: =IF(G57="y",$N$114,0)/12 | I57: =H57*$C$57 | K57: =IF(J57="y",$N$115,0)/12 | L57: =K57*$C$57 | N57: =IF(M57="y",$N$116,0)/12 | O57: =N57*$C$57 | Q57: =IF(P57="y",$N$117,0)/12 | R57: =Q57*$C$57 | T57: =IF(S57="y",$N$118,0)/12 | U57: =T57*$C$57 | W57: =IF(V57="y",$N$119,0)/12 | X57: =W57*$C$57 | Z57: =IF(Y57="y",$N$120,0)/12 | AA57: =Z57*$C$57 | AC57: =IF(AB57="y",$N$121,0)/12 | AD57: =AC57*$C57 | AF57: =IF(AE57="y",$N$122,0)/12 | AG57: =AF57*$C57 | AH57: =SUM(F57+I57+L57+O57+R57+U57+X57+AA57+AD57+AG57)
B58: Econoframe 3.0 | C58: ='Bonnell - Glass Pricing'!I8 | E58: =IF(D58="y",$N$113,0)/12 | F58: =E58*$C$58 | H58: =IF(G58="y",$N$114,0)/12 | I58: =H58*$C$58 | K58: =IF(J58="y",$N$115,0)/12 | L58: =K58*$C$58 | N58: =IF(M58="y",$N$116,0)/12 | O58: =N58*$C$58 | Q58: =IF(P58="y",$N$117,0)/12 | R58: =Q58*$C$58 | T58: =IF(S58="y",$N$118,0)/12 | U58: =T58*$C$58 | W58: =IF(V58="y",$N$119,0)/12 | X58: =W58*$C$58 | Z58: =IF(Y58="y",$N$120,0)/12 | AA58: =Z58*$C$58 | AC58: =IF(AB58="y",$N$121,0)/12 | AD58: =AC58*$C58 | AF58: =IF(AE58="y",$N$122,0)/12 | AG58: =AF58*$C58 | AH58: =SUM(F58+I58+L58+O58+R58+U58+X58+AA58+AD58+AG58)
B59: Waste | C59: 0.1 | F59: =SUM(F37:F58)*$C$59 | I59: =SUM(I37:I58)*$C$59 | L59: =SUM(L37:L58)*$C$59 | O59: =SUM(O37:O58)*$C$59 | R59: =SUM(R37:R58)*$C$59 | U59: =SUM(U37:U58)*$C$59 | X59: =SUM(X37:X58)*$C$59 | AA59: =SUM(AA37:AA58)*$C$59 | AD59: =SUM(AD37:AD58)*$C$59 | AG59: =SUM(AG37:AG58)*$C$59 | AH59: =SUM(F59+I59+L59+O59+R59+U59+X59+AA59+AD59+AG59)
B60: Brackets - Includes $10 for paint | C60: 20 | E60: =IF($L113>0,(($K113*4)+($L113*4)+$K113*$L113*4)+4,($K113*4)+4) | H60: =IF($L114>0,(($K114*4)+($L114*4)+$K114*$L114*4)+4,($K114*4)+4) | I60: =H60*$C60 | K60: =IF($L115>0,(($K115*4)+($L115*4)+$K115*$L115*4)+4,($K115*4)+4) | L60: =K60*$C60 | N60: =IF($L116>0,(($K116*4)+($L116*4)+$K116*$L116*4)+4,($K116*4)+4) | O60: =N60*$C60 | Q60: =IF($L117>0,(($K117*4)+($L117*4)+$K117*$L117*4)+4,($K117*4)+4) | R60: =Q60*$C60 | T60: =IF($L118>0,(($K118*4)+($L118*4)+$K118*$L118*4)+4,($K118*4)+4) | U60: =T60*$C60 | W60: =IF($L119>0,(($K119*4)+($L119*4)+$K119*$L119*4)+4,($K119*4)+4) | X60: =W60*$C60 | Z60: =IF($L120>0,(($K120*4)+($L120*4)+$K120*$L120*4)+4,($K120*4)+4) | AA60: =Z60*$C60 | AC60: =IF($L121>0,(($K121*4)+($L121*4)+$K121*$L121*4)+4,($K121*4)+4) | AD60: =AC60*$C60 | AF60: =IF($L122>0,(($K122*4)+($L122*4)+$K122*$L122*4)+4,($K122*4)+4) | AG60: =AF60*$C60 | AH60: =SUM(F60+I60+L60+O60+R60+U60+X60+AA60+AD60+AG60)
B61: Fasteners | C61: 9 | E61: =IF($L$113>0,(($K$113*12)+($L$113*12)+($K$113*$L$113*8))+16,($K$113*12)+16) | H61: =IF($L$114>0,(($K$114*12)+($L$114*12)+($K$114*$L$114*8))+16,($K$114*12)+16) | I61: =H61*$C61 | K61: =IF($L$115>0,(($K$115*12)+($L$115*12)+($K$115*$L$115*8))+16,($K$115*12)+16) | L61: =K61*$C61 | N61: =IF($L$116>0,(($K$116*12)+($L$116*12)+($K$116*$L$116*8))+16,($K$116*12)+16) | O61: =N61*$C61 | Q61: =IF($L$117>0,(($K$117*12)+($L$117*12)+($K$117*$L$117*8))+16,($K$117*12)+16) | R61: =Q61*$C61 | T61: =IF($L$118>0,(($K$118*12)+($L$118*12)+($K$118*$L$118*8))+16,($K$118*12)+16) | U61: =T61*$C61 | W61: =IF($L$119>0,(($K$119*12)+($L$119*12)+($K$119*$L$119*8))+16,($K$119*12)+16) | X61: =W61*$C61 | Z61: =IF($L$120>0,(($K$120*12)+($L$120*12)+($K$120*$L$120*8))+16,($K$120*12)+16) | AA61: =Z61*$C61 | AC61: =IF($L$121>0,(($K$121*12)+($L$121*12)+($K$121*$L$121*8))+16,($K$121*12)+16) | AD61: =AC61*$C61 | AF61: =IF($L$122>0,(($K$122*12)+($L$122*12)+($K$122*$L$122*8))+16,($K$122*12)+16) | AG61: =AF61*$C61 | AH61: =SUM(F61+I61+L61+O61+R61+U61+X61+AA61+AD61+AG61)
B62: Silicone | C62: 17 | E62: =E70/8 | F62: =E62*$C$62 | I62: =H62*$C$62 | L62: =K62*$C$62 | O62: =N62*$C$62 | R62: =Q62*$C$62 | U62: =T62*$C$62 | X62: =W62*$C$62 | AA62: =Z62*$C$62 | AD62: =AC62*$C$62 | AG62: =AF62*$C$62 | AH62: =SUM(F62+I62+L62+O62+R62+U62+X62+AA62+AD62+AG62)
B63: Gasket LF
B64: Perimeter | C64: 3 | E64: =I113 | F64: =E64*$C64 | H64: =I114 | I64: =H64*$C64 | K64: =I115 | L64: =K64*$C64 | N64: =I116 | O64: =N64*$C64 | Q64: =I117 | R64: =Q64*$C64 | T64: =I118 | U64: =T64*$C64 | W64: =I119 | X64: =W64*$C64 | Z64: =I120 | AA64: =Z64*$C64 | AC64: =I121 | AD64: =AC64*$C64 | AF64: =I122 | AG64: =AF64*$C64 | AH64: =SUM(F64+I64+L64+O64+R64+U64+X64+AA64+AD64+AG64)
B65: Rafters | C65: 3 | E65: =N113/12 | F65: =E65*$C65 | H65: =N114/12 | I65: =H65*$C65 | K65: =N115/12 | L65: =K65*$C65 | N65: =N116/12 | O65: =N65*$C65 | Q65: =N117/12 | R65: =Q65*$C65 | T65: =N118/12 | U65: =T65*$C65 | W65: =N119/12 | X65: =W65*$C65 | Z65: =N120/12 | AA65: =Z65*$C65 | AC65: =N121/12 | AD65: =AC65*$C65 | AF65: =N122/12 | AG65: =AF65*$C65 | AH65: =SUM(F65+I65+L65+O65+R65+U65+X65+AA65+AD65+AG65)
B66: Custom gasket | C66: 0 | AH66: =SUM(F66+I66+L66+O66+R66+U66+X66+AA66+AD66+AG66)
B67: 3m tape | C67: 0.95 | E67: =IF(D67="y",E64+E65,0) | F67: =E67*$C67 | H67: =IF(G67="y",H64+H65,0) | I67: =H67*$C67 | K67: =IF(J67="y",K64+K65,0) | L67: =K67*$C67 | N67: =IF(M67="y",N64+N65,0) | O67: =N67*$C67 | Q67: =IF(P67="y",Q64+Q65,0) | R67: =Q67*$C67 | T67: =IF(S67="y",T64+T65,0) | U67: =T67*$C67 | W67: =IF(V67="y",W64+W65,0) | X67: =W67*$C67 | Z67: =IF(Y67="y",Z64+Z65,0) | AA67: =Z67*$C67 | AC67: =IF(AB67="y",AC64+AC65,0) | AD67: =AC67*$C67 | AF67: =IF(AE67="y",AF64+AF65,0) | AG67: =AF67*$C67 | AH67: =SUM(F67+I67+L67+O67+R67+U67+X67+AA67+AD67+AG67)
B68: Shop Fabrication
B69: Man Hours | C69: 68 | F69: =E69*$C69 | I69: =H69*$C69 | L69: =K69*$C69 | O69: =N69*$C69 | R69: =Q69*$C69 | U69: =T69*$C69 | X69: =W69*$C69 | AA69: =Z69*$C69 | AD69: =AC69*$C69 | AG69: =AF69*$C69 | AH69: =SUM(F69+I69+L69+O69+R69+U69+X69+AA69+AD69+AG69)
B70: Paint by LF | C70: 31 | E70: =SUM(E64:E65) | F70: =E70*$C70 | H70: =SUM(H64:H65) | I70: =H70*$C70 | K70: =SUM(K64:K65) | L70: =K70*$C70 | N70: =SUM(N64:N65) | O70: =N70*$C70 | Q70: =SUM(Q64:Q65) | R70: =Q70*$C70 | T70: =SUM(T64:T65) | U70: =T70*$C70 | W70: =SUM(W64:W65) | X70: =W70*$C70 | Z70: =SUM(Z64:Z65) | AA70: =Z70*$C70 | AC70: =SUM(AC64:AC65) | AD70: =AC70*$C70 | AF70: =SUM(AF64:AF65) | AG70: =AF70*$C70 | AH70: =SUM(F70+I70+L70+O70+R70+U70+X70+AA70+AD70+AG70)
B71: Packaging | C71: 150 | E71: 1 | F71: =E71*$C71 | I71: =H71*$C71 | L71: =K71*$C71 | O71: =N71*$C71 | R71: =Q71*$C71 | U71: =T71*$C71 | X71: =W71*$C71 | AA71: =Z71*$C71 | AD71: =AC71*$C71 | AG71: =AF71*$C71 | AH71: =SUM(F71+I71+L71+O71+R71+U71+X71+AA71+AD71+AG71)
B72: Additional Charges - Adds with no fees
B73: Engineering
B74: Stamped Drawings | C74: 540 | F74: =E74*$C74 | I74: =H74*$C74 | L74: =K74*$C74 | O74: =N74*$C74 | R74: =Q74*$C74 | U74: =T74*$C74 | X74: =W74*$C74 | AA74: =Z74*$C74 | AD74: =AC74*$C74 | AG74: =AF74*$C74 | AH74: =SUM(F74+I74+L74+O74+R74+U74+X74+AA74+AD74+AG74)
B75: Calculations glass only No IGU | C75: 540 | F75: =E75*$C75 | I75: =H75*$C75 | L75: =K75*$C75 | O75: =N75*$C75 | R75: =Q75*$C75 | U75: =T75*$C75 | X75: =W75*$C75 | AA75: =Z75*$C75 | AD75: =AC75*$C75 | AG75: =AF75*$C75 | AH75: =SUM(F75+I75+L75+O75+R75+U75+X75+AA75+AD75+AG75)
B76: Calculations glass only with IGU | C76: 720 | F76: =E76*$C76 | I76: =H76*$C76 | L76: =K76*$C76 | O76: =N76*$C76 | R76: =Q76*$C76 | U76: =T76*$C76 | X76: =W76*$C76 | AA76: =Z76*$C76 | AD76: =AC76*$C76 | AG76: =AF76*$C76 | AH76: =SUM(F76+I76+L76+O76+R76+U76+X76+AA76+AD76+AG76)
B77: Calculations frame & glass no IGU | C77: 1500 | F77: =E77*$C77 | I77: =H77*$C77 | L77: =K77*$C77 | O77: =N77*$C77 | R77: =Q77*$C77 | U77: =T77*$C77 | X77: =W77*$C77 | AA77: =Z77*$C77 | AD77: =AC77*$C77 | AG77: =AF77*$C77 | AH77: =SUM(F77+I77+L77+O77+R77+U77+X77+AA77+AD77+AG77)
B78: Calculations frame & glass with IGU | C78: 1680 | F78: =E78*$C78 | I78: =H78*$C78 | L78: =K78*$C78 | O78: =N78*$C78 | R78: =Q78*$C78 | U78: =T78*$C78 | X78: =W78*$C78 | AA78: =Z78*$C78 | AD78: =AC78*$C78 | AG78: =AF78*$C78 | AH78: =SUM(F78+I78+L78+O78+R78+U78+X78+AA78+AD78+AG78)
B79: Custom Upcharge | C79: 0.55 | F79: =E79*$C79 | I79: =H79*$C79 | L79: =K79*$C79 | O79: =N79*$C79 | R79: =Q79*$C79 | U79: =T79*$C79 | X79: =W79*$C79 | AA79: =Z79*$C79 | AD79: =AC79*$C79 | AG79: =AF79*$C79 | AH79: =SUM(F79+I79+L79+O79+R79+U79+X79+AA79+AD79+AG79)
B80: Shop Drawings | C80: 75 | F80: =E80*$C$80 | I80: =H80*$C$80 | L80: =K80*$C$80 | O80: =N80*$C$80 | R80: =Q80*$C$80 | U80: =T80*$C$80 | X80: =W80*$C$80 | AA80: =Z80*$C$80 | AD80: =AC80*$C$80 | AG80: =AF80*$C$80 | AH80: =SUM(F80+I80+L80+O80+R80+U80+X80+AA80+AD80+AG80)
E81: Qty Pricing Below | H81: Qty Pricing Below | K81: Qty Pricing Below | N81: Qty Pricing Below | Q81: Qty Pricing Below | T81: Qty Pricing Below | W81: Qty Pricing Below | Z81: Qty Pricing Below | AC81: Qty Pricing Below | AF81: Qty Pricing Below
B82: Sub Total | E82: =IF($J$113>1,F82*$J$113,"") | F82: =SUM(F9:F71) | H82: =IF($J$114>1,I82*$J$114,"") | I82: =SUM(I9:I71) | K82: =IF($J$115>1,L82*$J$115,"") | L82: =SUM(L9:L71) | N82: =IF($J$116>1,O82*$J$116,"") | O82: =SUM(O9:O71) | Q82: =IF($J$117>1,R82*$J$117,"") | R82: =SUM(R9:R71) | T82: =IF($J$118>1,U82*$J$118,"") | U82: =SUM(U9:U71) | W82: =IF($J$119>1,X82*$J$119,"") | X82: =SUM(X9:X71) | Z82: =IF($J$120>1,AA82*$J$120,"") | AA82: =SUM(AA9:AA71) | AC82: =IF($J$121>1,AD82*$J$121,"") | AD82: =SUM(AD9:AD71) | AF82: =IF($J$122>1,AG82*$J$122,"") | AG82: =SUM(AG9:AG71) | AH82: =SUM(F82+I82+L82+O82+R82+U82+X82+AA82+AD82+AG82)
B83: Shipping | C83: 350 | F83: =$C$83*E83 | I83: =$C$83*H83 | L83: =$C$83*K83 | O83: =$C$83*N83 | R83: =$C$83*Q83 | U83: =$C$83*T83 | X83: =$C$83*W83 | AA83: =$C$83*Z83 | AD83: =$C$83*AC83 | AG83: =$C$83*AF83 | AH83: =SUM(F83+I83+L83+O83+R83+U83+X83+AA83+AD83+AG83)
B84: Overhead | C84: 0.1 | E84: =IF($J$113>1,F84*$J$113,"") | F84: =SUM(F82:F83)*$C$84 | H84: =IF($J$114>1,I84*$J$114,"") | I84: =SUM(I82:I83)*$C$84 | K84: =IF($J$115>1,L84*$J$115,"") | L84: =SUM(L82:L83)*$C$84 | N84: =IF($J$116>1,O84*$J$116,"") | O84: =SUM(O82:O83)*$C$84 | Q84: =IF($J$117>1,R84*$J$117,"") | R84: =SUM(R82:R83)*$C$84 | T84: =IF($J$118>1,U84*$J$118,"") | U84: =SUM(U82:U83)*$C$84 | W84: =IF($J$119>1,X84*$J$119,"") | X84: =SUM(X82:X83)*$C$84 | Z84: =IF($J$120>1,AA84*$J$120,"") | AA84: =SUM(AA82:AA83)*$C$84 | AC84: =IF($J$121>1,AD84*$J$121,"") | AD84: =SUM(AD82:AD83)*$C$84 | AF84: =IF($J$122>1,AG84*$J$122,"") | AG84: =SUM(AG82:AG83)*$C$84 | AH84: =SUM(F84+I84+L84+O84+R84+U84+X84+AA84+AD84+AG84)
B85: Profit | C85: 0.5 | E85: =IF($J$113>1,F85*$J$113,"") | F85: =SUM(F82:F84)*$C$85 | H85: =IF($J$114>1,I85*$J$114,"") | I85: =SUM(I82:I84)*$C$85 | K85: =IF($J$115>1,L85*$J$115,"") | L85: =SUM(L82:L84)*$C$85 | N85: =IF($J$116>1,O85*$J$116,"") | O85: =SUM(O82:O84)*$C$85 | Q85: =IF($J$117>1,R85*$J$117,"") | R85: =SUM(R82:R84)*$C$85 | T85: =IF($J$118>1,U85*$J$118,"") | U85: =SUM(U82:U84)*$C$85 | W85: =IF($J$119>1,X85*$J$119,"") | X85: =SUM(X82:X84)*$C$85 | Z85: =IF($J$120>1,AA85*$J$120,"") | AA85: =SUM(AA82:AA84)*$C$85 | AC85: =IF($J$121>1,AD85*$J$121,"") | AD85: =SUM(AD82:AD84)*$C$85 | AF85: =IF($J$122>1,AG85*$J$122,"") | AG85: =SUM(AG82:AG84)*$C$85 | AH85: =SUM(F85+I85+L85+O85+R85+U85+X85+AA85+AD85+AG85)
B86: Insurance | C86: 0.06 | E86: =IF($J$113>1,F86*$J$113,"") | F86: =SUM(F82:F85)*$C$86 | H86: =IF($J$114>1,I86*$J$114,"") | I86: =SUM(I82:I85)*$C$86 | K86: =IF($J$115>1,L86*$J$115,"") | L86: =SUM(L82:L85)*$C$86 | N86: =IF($J$116>1,O86*$J$116,"") | O86: =SUM(O82:O85)*$C$86 | Q86: =IF($J$117>1,R86*$J$117,"") | R86: =SUM(R82:R85)*$C$86 | T86: =IF($J$118>1,U86*$J$118,"") | U86: =SUM(U82:U85)*$C$86 | W86: =IF($J$119>1,X86*$J$119,"") | X86: =SUM(X82:X85)*$C$86 | Z86: =IF($J$120>1,AA86*$J$120,"") | AA86: =SUM(AA82:AA85)*$C$86 | AC86: =IF($J$121>1,AD86*$J$121,"") | AD86: =SUM(AD82:AD85)*$C$86 | AF86: =IF($J$122>1,AG86*$J$122,"") | AG86: =SUM(AG82:AG85)*$C$86 | AH86: =SUM(F86+I86+L86+O86+R86+U86+X86+AA86+AD86+AG86)
B87: Sales Rep Commission | C87: 0.05 | E87: =IF($J$113>1,F87*$J$113,"") | F87: =IF(D87="Y",SUM(F82:F86)*$C$87,"0") | H87: =IF($J$114>1,I87*$J$114,"") | I87: =IF(G87="Y",SUM(I82:I86)*$C$87,"0") | K87: =IF($J$115>1,L87*$J$115,"") | L87: =IF(J87="Y",SUM(L82:L86)*$C$87,"0") | N87: =IF($J$116>1,O87*$J$116,"") | O87: =IF(M87="Y",SUM(O82:O86)*$C$87,"0") | Q87: =IF($J$117>1,R87*$J$117,"") | R87: =IF(P87="Y",SUM(R82:R86)*$C$87,"0") | T87: =IF($J$118>1,U87*$J$118,"") | U87: =IF(S87="Y",SUM(U82:U86)*$C$87,"0") | W87: =IF($J$119>1,X87*$J$119,"") | X87: =IF(V87="Y",SUM(X82:X86)*$C$87,"0") | Z87: =IF($J$120>1,AA87*$J$120,"") | AA87: =IF(Y87="Y",SUM(AA82:AA86)*$C$87,"0") | AC87: =IF($J$121>1,AD87*$J$121,"") | AD87: =IF(AB87="Y",SUM(AD82:AD86)*$C$87,"0") | AF87: =IF($J$122>1,AG87*$J$122,"") | AG87: =IF(AE87="Y",SUM(AG82:AG86)*$C$87,"0") | AH87: =SUM(F87+I87+L87+O87+R87+U87+X87+AA87+AD87+AG87)
B88: Duty | C88: 0.055 | E88: =IF($J$113>1,F88*$J$113,"") | F88: =IF(D88="Y",SUM(F9:F15)*$C$88,"0") | H88: =IF($J$114>1,I88*$J$114,"") | I88: =IF(D88="Y",SUM(I9:I15)*$C$88,"0") | K88: =IF($J$115>1,L88*$J$115,"") | L88: =IF(D88="Y",SUM(L9:L15)*$C$88,"0") | N88: =IF($J$116>1,O88*$J$116,"") | O88: =IF(D88="Y",SUM(O9:O15)*$C$88,"0") | Q88: =IF($J$117>1,R88*$J$117,"") | R88: =IF(D88="Y",SUM(R9:R15)*$C$88,"0") | T88: =IF($J$118>1,U88*$J$118,"") | U88: =IF(D88="Y",SUM(U9:U15)*$C$88,"0") | W88: =IF($J$119>1,X88*$J$119,"") | X88: =IF(D88="Y",SUM(X9:X15)*$C$88,"0") | Z88: =IF($J$120>1,AA88*$J$120,"") | AA88: =IF(D88="Y",SUM(AA9:AA15)*$C$88,"0") | AC88: =IF($J$121>1,AD88*$J$121,"") | AD88: =IF(D88="Y",SUM(AD9:AD15)*$C$88,"0") | AF88: =IF($J$122>1,AG88*$J$122,"") | AG88: =IF(D88="Y",SUM(AG9:AG15)*$C$88,"0") | AH88: =SUM(F88+I88+L88+O88+R88+U88+X88+AA88+AD88+AG88)
B89: Transgroup Fees | C89: =SUM(95+55+45) | F89: =IF(D89="Y",$C$89/J113,"0") | I89: =IF(D89="Y",$C$89/J114,"0") | L89: =IF(D89="Y",$C$89/J115,"0") | O89: =IF(D89="Y",$C$89/J116,"0") | R89: =IF(D89="Y",$C$89/J117,"0") | U89: =IF(D89="Y",$C$89/J118,"0") | X89: =IF(D89="Y",$C$89/J119,"0") | AA89: =IF(D89="Y",$C$89/J120,"0") | AD89: =IF(D89="Y",$C$89/J121,"0") | AG89: =IF(D89="Y",$C$89/J122,"0") | AH89: =SUM(F89+I89+L89+O89+R89+U89+X89+AA89+AD89+AG89)
B90: TOTAL | E90: =IF($J$113>1,F90*$J$113,"") | F90: =SUM(F82:F89) | H90: =IF($J$114>1,I90*$J$114,"") | I90: =SUM(I82:I89) | K90: =IF($J$115>1,L90*$J$115,"") | L90: =SUM(L82:L89) | N90: =IF($J$116>1,O90*$J$116,"") | O90: =SUM(O82:O89) | Q90: =IF($J$117>1,R90*$J$117,"") | R90: =SUM(R82:R89) | T90: =IF($J$118>1,U90*$J$118,"") | U90: =SUM(U82:U89) | W90: =IF($J$119>1,X90*$J$119,"") | X90: =SUM(X82:X89) | Z90: =IF($J$120>1,AA90*$J$120,"") | AA90: =SUM(AA82:AA89) | AC90: =IF($J$121>1,AD90*$J$121,"") | AD90: =SUM(AD82:AD89) | AF90: =IF($J$122>1,AG90*$J$122,"") | AG90: =SUM(AG82:AG89) | AH90: =SUM(F90+I90+L90+O90+R90+U90+X90+AA90+AD90+AG90)
B91: Mark up | C91: 0.1 | E91: =IF($J$113>1,F91*$J$113,"") | F91: =IF(D91="Y",F90*$C$91,"0") | H91: =IF($J$114>1,I91*$J$114,"") | I91: =IF(G91="Y",I90*$C$91,"0") | K91: =IF($J$115>1,L91*$J$115,"") | L91: =IF(J91="Y",L90*$C$91,"0") | N91: =IF($J$116>1,O91*$J$116,"") | O91: =IF(M91="Y",O90*$C$91,"0") | Q91: =IF($J$117>1,R91*$J$117,"") | R91: =IF(P91="Y",R90*$C$91,"0") | T91: =IF($J$118>1,U91*$J$118,"") | U91: =IF(S91="Y",U90*$C$91,"0") | W91: =IF($J$119>1,X91*$J$119,"") | X91: =IF(V91="Y",X90*$C$91,"0") | Z91: =IF($J$120>1,AA91*$J$120,"") | AA91: =IF(Y91="Y",AA90*$C$91,"0") | AC91: =IF($J$121>1,AD91*$J$121,"") | AD91: =IF(AB91="Y",AD90*$C$91,"0") | AF91: =IF($J$122>1,AG91*$J$122,"") | AG91: =IF(AE91="Y",AG90*$C$91,"0") | AH91: =SUM(F91+I91+L91+O91+R91+U91+X91+AA91+AD91+AG91)
B92: Discount Amount | C92: 0.2 | E92: =IF($J$113>1,F92*$J$113,"") | F92: =IF(D92="Y",F90*$C$92,"0") | H92: =IF($J$114>1,I92*$J$114,"") | I92: =IF(G92="Y",I90*$C$92,"0") | K92: =IF($J$115>1,L92*$J$115,"") | L92: =IF(J92="Y",L90*$C$92,"0") | N92: =IF($J$116>1,O92*$J$116,"") | O92: =IF(M92="Y",O90*$C$92,"0") | Q92: =IF($J$117>1,R92*$J$117,"") | R92: =IF(P92="Y",R90*$C$92,"0") | T92: =IF($J$118>1,U92*$J$118,"") | U92: =IF(S92="Y",U90*$C$92,"0") | W92: =IF($J$119>1,X92*$J$119,"") | X92: =IF(V92="Y",X90*$C$92,"0") | Z92: =IF($J$120>1,AA92*$J$120,"") | AA92: =IF(Y92="Y",AA90*$C$92,"0") | AC92: =IF($J$121>1,AD92*$J$121,"") | AD92: =IF(AB92="Y",AD90*$C$92,"0") | AF92: =IF($J$122>1,AG92*$J$122,"") | AG92: =IF(AE92="Y",AG90*$C$92,"0") | AH92: =SUM(F92+I92+L92+O92+R92+U92+X92+AA92+AD92+AG92)
B93: FINAL PRICE | E93: =IF($J$113>1,F93*$J$113,"") | F93: =SUM(F90+F91-F92)+SUM(F74:F80) | H93: =IF($J$114>1,I93*$J$114,"") | I93: =SUM(I90+I91-I92)+SUM(I74:I80) | K93: =IF($J$115>1,L93*$J$115,"") | L93: =SUM(L90+L91-L92)+SUM(L74:L80) | N93: =IF($J$116>1,O93*$J$116,"") | O93: =SUM(O90+O91-O92)+SUM(O74:O80) | Q93: =IF($J$117>1,R93*$J$117,"") | R93: =SUM(R90+R91-R92)+SUM(R74:R80) | T93: =IF($J$118>1,U93*$J$118,"") | U93: =SUM(U90+U91-U92)+SUM(U74:U80) | W93: =IF($J$119>1,X93*$J$119,"") | X93: =SUM(X90+X91-X92)+SUM(X74:X80) | Z93: =IF($J$120>1,AA93*$J$120,"") | AA93: =SUM(AA90+AA91-AA92)+SUM(AA74:AA80) | AC93: =IF($J$121>1,AD93*$J$121,"") | AD93: =SUM(AD90+AD91-AD92)+SUM(AD74:AD80) | AF93: =IF($J$121>1,AG93*$J$121,"") | AG93: =SUM(AG90+AG91-AG92)+SUM(AG74:AG80) | AH93: =SUM(F93+I93+L93+O93+R93+U93+X93+AA93+AD93+AG93)
B94: Unit Cost - $ per Sq. Ft | F94: =F93/H113 | I94: =I93/H114 | L94: =L93/H115 | O94: =O93/H116 | R94: =R93/H117 | U94: =U93/H118 | X94: =X93/H119 | AA94: =AA93/H120 | AD94: =AD93/H121 | AG94: =AG93/H122
B95: Railing Cost - $ per LF. | E95: =IF(C32="Y",((E31+E32+E34)/D32),IF(C33="Y",((E31+E33+E34)/D33),"")) | F95: =IF(D32="Y",(F31+F32+F34),"")
B96: Total Sq. Footage of job | C96: =H123 | AH96: =H123
B97: Weight
B98: Glass Total - lbs. | E98: =IF(E9>0,E9*$C$151,IF(E10>0,E10*$C$152,IF(E11>0,E11*$C$153,IF(E12>0,E12*$C$151,IF(E13>0,E13*$C$151,""))))) | F98: lbs. | H98: =IF(H9>0,H9*$C$151,IF(H10>0,H10*$C$152,IF(H11>0,H11*$C$153,IF(H12>0,H12*$C$151,IF(H13>0,H13*$C$151,""))))) | I98: lbs. | K98: =IF(K9>0,K9*$C$151,IF(K10>0,K10*$C$152,IF(K11>0,K11*$C$153,IF(K12>0,K12*$C$151,IF(K13>0,K13*$C$151,""))))) | L98: lbs. | N98: =IF(N9>0,N9*$C$151,IF(N10>0,N10*$C$152,IF(N11>0,N11*$C$153,IF(N12>0,N12*$C$151,IF(N13>0,N13*$C$151,""))))) | O98: lbs. | Q98: =IF(Q9>0,Q9*$C$151,IF(Q10>0,Q10*$C$152,IF(Q11>0,Q11*$C$153,IF(Q12>0,Q12*$C$151,IF(Q13>0,Q13*$C$151,""))))) | R98: lbs. | T98: =IF(T9>0,T9*$C$151,IF(T10>0,T10*$C$152,IF(T11>0,T11*$C$153,IF(T12>0,T12*$C$151,IF(T13>0,T13*$C$151,""))))) | U98: lbs. | W98: =IF(W9>0,W9*$C$151,IF(W10>0,W10*$C$152,IF(W11>0,W11*$C$153,IF(W12>0,W12*$C$151,IF(W13>0,W13*$C$151,""))))) | X98: lbs. | Z98: =IF(Z9>0,Z9*$C$151,IF(Z10>0,Z10*$C$152,IF(Z11>0,Z11*$C$153,IF(Z12>0,Z12*$C$151,IF(Z13>0,Z13*$C$151,""))))) | AA98: lbs. | AC98: =IF(AC9>0,AC9*$C$151,IF(AC10>0,AC10*$C$152,IF(AC11>0,AC11*$C$153,IF(AC12>0,AC12*$C$151,IF(AC13>0,AC13*$C$151,""))))) | AD98: lbs. | AF98: =IF(AF9>0,AF9*$C$151,IF(AF10>0,AF10*$C$152,IF(AF11>0,AF11*$C$153,IF(AF12>0,AF12*$C$151,IF(AF13>0,AF13*$C$151,""))))) | AG98: lbs. | AH98: =SUM(E98+H98+K98+N98+Q98+T98+W98+Z98) | AI98: lbs.
B99: Each Glass Panel - lbs. | E99: =E98/G113 | F99: =E99+150 | H99: =H98/G114 | I99: lbs. | K99: =K98/G115 | L99: lbs. | N99: =N98/G116 | O99: lbs. | Q99: =Q98/G117 | R99: lbs. | T99: =T98/G118 | U99: lbs. | W99: =W98/G119 | X99: lbs. | Z99: =Z98/G120 | AA99: lbs. | AC99: =AC98/G121 | AD99: lbs. | AF99: =AF98/G122 | AG99: lbs.
B100: Frame weight - lbs. | E100: ='Weights - Descriptions'!E22 | F100: =E100+200 | H100: ='Weights - Descriptions'!F22 | I100: lbs. | K100: ='Weights - Descriptions'!G22 | L100: lbs. | N100: ='Weights - Descriptions'!H22 | O100: lbs. | Q100: ='Weights - Descriptions'!I22 | R100: lbs. | T100: ='Weights - Descriptions'!J22 | U100: lbs. | W100: ='Weights - Descriptions'!K22 | X100: lbs. | Z100: ='Weights - Descriptions'!L22 | AA100: lbs. | AC100: ='Weights - Descriptions'!M22 | AD100: lbs. | AF100: ='Weights - Descriptions'!N22 | AG100: lbs. | AH100: =SUM(E100+H100+K100+N100+Q100+T100+W100+Z100) | AI100: lbs.
B101: Total (glass and frame) - lbs. per unit | E101: =SUM(E100+E98) | F101: lbs. | H101: =SUM(H100+H98) | I101: lbs. | K101: =SUM(K100+K98) | L101: lbs. | N101: =SUM(N100+N98) | O101: lbs. | Q101: =SUM(Q100+Q98) | R101: lbs. | T101: =SUM(T100+T98) | U101: lbs. | W101: =SUM(W100+W98) | X101: lbs. | Z101: =SUM(Z100+Z98) | AA101: lbs. | AC101: =SUM(AC100+AC98) | AD101: lbs. | AF101: =SUM(AF100+AF98) | AG101: lbs. | AH101: =SUM(E101+H101+K101+N101+Q101+T101+W101+Z101) | AI101: lbs.
...

Sheet Proposal
J2: Proposal # | K2: ='Pricing Worksheet'!I2
J3: Date: | K3: =TODAY()
J4: Project Name: | K4: ='Pricing Worksheet'!C2
J5: Project Address: | K5: ='Pricing Worksheet'!F2
J6: Project Type: | K6: ='Pricing Worksheet'!C4
J7: Architect: | K7: ='Pricing Worksheet'!F4
J8: Contact: | K8: ='Pricing Worksheet'!C3
J9: Phone: | K9: ='Pricing Worksheet'!I3
B10: 6 Aaron Way, Sparta, NJ 07871 O - 862-701-5320 | J10: Email: | K10: ='Pricing Worksheet'!L3
B11: www.glassflooringsystems.com | J11: Quoted By: | K11: ='Pricing Worksheet'!L2
B14: Thank you for your interest in Glass Flooring Systems. The following quote is for (1 Qty.) 18" x 30" Series 1000 SkyFloor® walkable skylight. This are complete systems which consist of our proprietary structural, thermally broken, recessed perimeter framing (modified rear flange removal on all sides) with integrated setting gaskets, perimeter LED lighting channel and one (1) structural walkable glass panel with tested anti-slip top layer. Framing to arrive fully welded, glazing to be performed on site - by others. The make-up of the glass panel is listed below. Please review and let us know if you have any questions or require additional information.
B16: Once you receive your SkyFloor® system all that is required for installation is three simple steps.
B17: 1. Set assembled SkyFloor® system at prepared opening.
B18: 2. Secure assembled SkyFloor® system at prepared opening.
B19: 3. Complete field waterproofing.
B21: Glass Flooring Systems to supply as follows:
B22: Unit | C22: Drawing | D22: Drawing Date | E22: Location | F22: Exposed Frame Dimension (inches) | J22: Description
B23: ='Pricing Worksheet'!D113 | C23: ='Pricing Worksheet'!C113 | D23: 9.27.24 | E23: ='Pricing Worksheet'!B113 | F23: ='Pricing Worksheet'!E113 | G23: x | H23: ='Pricing Worksheet'!F113 | I23: (1 Qty.) 18" x 30" Series 1000 SkyFloor® walkable skylight - consisting of one (1) glass panel
B24: ='Pricing Worksheet'!D114 | C24: ='Pricing Worksheet'!C114 | E24: ='Pricing Worksheet'!B114 | F24: ='Pricing Worksheet'!E114 | G24: x | H24: ='Pricing Worksheet'!F114 | J24: Description
B25: ='Pricing Worksheet'!D115 | C25: ='Pricing Worksheet'!C115 | E25: ='Pricing Worksheet'!B115 | F25: ='Pricing Worksheet'!E115 | G25: x | H25: ='Pricing Worksheet'!F115 | J25: Description
B26: ='Pricing Worksheet'!D116 | C26: ='Pricing Worksheet'!C116 | E26: ='Pricing Worksheet'!B116 | F26: ='Pricing Worksheet'!E116 | G26: x | H26: ='Pricing Worksheet'!F116 | J26: Description
B27: ='Pricing Worksheet'!D117 | C27: ='Pricing Worksheet'!C117 | E27: ='Pricing Worksheet'!B117 | F27: ='Pricing Worksheet'!E117 | G27: x | H27: ='Pricing Worksheet'!F117 | J27: Description
B28: ='Pricing Worksheet'!D118 | C28: ='Pricing Worksheet'!C118 | E28: ='Pricing Worksheet'!B118 | F28: ='Pricing Worksheet'!E118 | G28: x | H28: ='Pricing Worksheet'!F118 | J28: Description
B29: ='Pricing Worksheet'!D119 | C29: ='Pricing Worksheet'!C119 | E29: ='Pricing Worksheet'!B119 | F29: ='Pricing Worksheet'!E119 | G29: x | H29: ='Pricing Worksheet'!F119 | J29: Description
B30: ='Pricing Worksheet'!D120 | C30: ='Pricing Worksheet'!C120 | E30: ='Pricing Worksheet'!B120 | F30: ='Pricing Worksheet'!E120 | G30: x | H30: ='Pricing Worksheet'!F120 | J30: Description
B31: ='Pricing Worksheet'!D121 | C31: ='Pricing Worksheet'!C121 | E31: ='Pricing Worksheet'!B121 | F31: ='Pricing Worksheet'!E121 | G31: x | H31: ='Pricing Worksheet'!F121 | J31: Description
B32: ='Pricing Worksheet'!D122 | C32: ='Pricing Worksheet'!C122 | E32: ='Pricing Worksheet'!B122 | F32: ='Pricing Worksheet'!E122 | G32: x | H32: ='Pricing Worksheet'!F122 | J32: Description
B34: Glazing
B35: Glass Make-up
B36: 10mm top layer – low iron tempered anti-slip texture. Final texture TBD.
B37: 1.52mm interlayer – PVB
B38: 10mm middle layer – low iron tempered
B39: 1.52mm interlayer – PVB
B40: 10mm bottom layer – low iron tempered
B42: Glass Make-up
B43: 10mm top layer – low iron tempered anti-slip texture. Final texture TBD.
B44: 1.52mm interlayer – DG Structural
B45: 10mm middle layer – low iron tempered
B46: 1.52mm interlayer – DG Structural
... B68: Pricing
B69: Unit A | D69: =I23 | J69: ='Pricing Worksheet'!F93*'Pricing Worksheet'!J113 | K69: Anti-Slip surface texture is included in base price. See our Terms and Conditions #20 for the texture options included in the base price. The Seeded Organic™ and NanoDot™ textures are available - at an additional cost listed below.
B70: Unit B | D70: =J24 | J70: ='Pricing Worksheet'!I93*'Pricing Worksheet'!J114
B71: Unit C | D71: =J25 | J71: ='Pricing Worksheet'!L93*'Pricing Worksheet'!J115
B72: Unit D | D72: =J26 | J72: ='Pricing Worksheet'!O93*'Pricing Worksheet'!J116
B73: Unit E | D73: =J27 | J73: ='Pricing Worksheet'!R93*'Pricing Worksheet'!J117
B74: Unit F | D74: =J28 | J74: ='Pricing Worksheet'!U93*'Pricing Worksheet'!J118
B75: Unit G | D75: =J29 | J75: ='Pricing Worksheet'!X93*'Pricing Worksheet'!J119
B76: Unit H | D76: =J30 | J76: ='Pricing Worksheet'!AA93*'Pricing Worksheet'!J120
B77: Unit I | D77: Description | J77: ='Pricing Worksheet'!AD93*'Pricing Worksheet'!J121
B78: Unit J | D78: Description | J78: ='Pricing Worksheet'!AG93*'Pricing Worksheet'!J122
B79: Total | J79: =SUM(J69:J78)
B80: Plus Tax if applicable / HST & Duty to be paid by purchaser
B82: Add - Seeded Organic™ anti-slip texture (Optional)
B83: Unit A | D83: Add | E83: ='Pricing Worksheet'!F105 | F83: Initial here ________ if you approve additional charge for our Seeded Organic™ texture.
B84: Unit B | D84: add | E84: ='Pricing Worksheet'!I105 | F84: Initial here ________ if you approve additional charge for our Seeded Organic™ texture.
B85: Unit C | D85: add | E85: ='Pricing Worksheet'!L105 | F85: Initial here ________ if you approve additional charge for our Seeded Organic™ texture.
B86: Unit D | D86: add | E86: ='Pricing Worksheet'!O105 | F86: Initial here ________ if you approve additional charge for our Seeded Organic™ texture.
B87: Unit E | D87: add | E87: ='Pricing Worksheet'!R105 | F87: Initial here ________ if you approve additional charge for our Seeded Organic™ texture.
B88: Unit F | D88: add | E88: ='Pricing Worksheet'!U105 | F88: Initial here ________ if you approve additional charge for our Seeded Organic™ texture.
B89: Unit G | D89: add | E89: ='Pricing Worksheet'!X105 | F89: Initial here ________ if you approve additional charge for our Seeded Organic™ texture.
B90: Unit H | D90: add | E90: ='Pricing Worksheet'!AA105 | F90: Initial here ________ if you approve additional charge for our Seeded Organic™ texture.
B91: Unit I | D91: add | E91: ='Pricing Worksheet'!AD105 | F91: Initial here ________ if you approve additional charge for our Seeded Organic™ texture.
B92: Unit J | D92: add | E92: ='Pricing Worksheet'!AG105 | F92: Initial here ________ if you approve additional charge for our Seeded Organic™ texture.
B93: **Due to the production processes required in the manufacture of our (Kiln / Cast) Seeded Organic® anti-slip texture, the product may develop some imperfections such as some slight distortion or small bubbles within the make-up of the laminated assembly. These will not affect the structural integrity of the glass panel nor shall they be considered a defect.**
B97: Add - NanoDot™ anti-slip texture (Optional)
B98: Unit A | D98: Add | E98: ='Pricing Worksheet'!F108 | F98: Initial here ________ if you approve additional charge for our NanoDot™ texture.
B99: Unit B | D99: add | E99: ='Pricing Worksheet'!I108 | F99: Initial here ________ if you approve additional charge for our NanoDot™ texture.
B100: Unit C | D100: add | E100: ='Pricing Worksheet'!L108 | F100: Initial here ________ if you approve additional charge for our NanoDot™ texture.
B101: Unit D | D101: add | E101: ='Pricing Worksheet'!O108 | F101: Initial here ________ if you approve additional charge for our NanoDot™ texture.
B102: Unit E | D102: add | E102: ='Pricing Worksheet'!R108 | F102: Initial here ________ if you approve additional charge for our NanoDot™ texture.
B103: Unit F | D103: add | E103: ='Pricing Worksheet'!U108 | F103: Initial here ________ if you approve additional charge for our NanoDot™ texture.
B104: Unit G | D104: add | E104: ='Pricing Worksheet'!X108 | F104: Initial here ________ if you approve additional charge for our NanoDot™ texture.
B105: Unit H | D105: add | E105: ='Pricing Worksheet'!AA108 | F105: Initial here ________ if you approve additional charge for our NanoDot™ texture.
B106: Unit I | D106: add | E106: ='Pricing Worksheet'!AD108 | F106: Initial here ________ if you approve additional charge for our NanoDot™ texture.
B107: Unit J | D107: add | E107: ='Pricing Worksheet'!AG108 | F107: Initial here ________ if you approve additional charge for our NanoDot™ texture.
B108: * Lead time for Nano Dot is 10-12 weeks
B110: Heat Soak Testing
B111: Unit A | D111: add | E111: ='Pricing Worksheet'!F107 | F111: Initial here ________ if you approve additional charge for Heat Soak Testing.
B112: Unit B | D112: add | E112: ='Pricing Worksheet'!I107 | F112: Initial here ________ if you approve additional charge for Heat Soak Testing.
B113: Unit C | D113: add | E113: ='Pricing Worksheet'!L107 | F113: Initial here ________ if you approve additional charge for Heat Soak Testing.
B114: Unit D | D114: add | E114: ='Pricing Worksheet'!O107 | F114: Initial here ________ if you approve additional charge for Heat Soak Testing.
B115: Unit E | D115: add | E115: ='Pricing Worksheet'!R107 | F115: Initial here ________ if you approve additional charge for Heat Soak Testing.
B116: Unit F | D116: add | E116: ='Pricing Worksheet'!U107 | F116: Initial here ________ if you approve additional charge for Heat Soak Testing.
B117: Unit G | D117: add | E117: ='Pricing Worksheet'!X107 | F117: Initial here ________ if you approve additional charge for Heat Soak Testing.
B118: Unit H | D118: add | E118: ='Pricing Worksheet'!AA107 | F118: Initial here ________ if you approve additional charge for Heat Soak Testing.
B119: Unit I | D119: add | E119: ='Pricing Worksheet'!AD107 | F119: Initial here ________ if you approve additional charge for Heat Soak Testing.
B120: Unit J | D120: add | E120: ='Pricing Worksheet'!AG107 | F120: Initial here ________ if you approve additional charge for Heat Soak Testing.
B122: Shipping and Crating | H122: Add | J122: =681.01*1.1 | K122: Shipping to L6J 1G3 via common carrier
B123: Initial here ________ if you require shipping and crating and approve additional charge. | K123: HST & Duty to be paid by purchaser
B124: Customers are responsible for the unloading of the shipping/delivery vehicles. This responsibility includes, but is not limited to, arranging for labor and securing the necessary material handling equipment. For any questions regarding the specifics of your shipment’s arrival, please contact us to ensure that you are fully prepared for the unloading process upon delivery.
B125: **Due to current market conditions - shipping costs are estimated and subject to change. Final cost will be determined upon shipment date**
B127: Lift gate service at delivery | H127: Add | J127: 145
B128: Initial here ________ if you require lift gate for delivery and approve additional charge as noted.
B130: Engineering
B131: Glass Flooring Systems Inc. offers a wide range of pre-engineered products. Engineering is not included in this proposal. Glass Flooring Systems Inc. can provide a complete engineering analysis & report including stamped shop drawings with glass specific calculations for each individual state. Each project has different engineering requirements. Please contact us if you require engineering. Glass Flooring Systems Inc. will provide pricing for engineering based on your requirements. It is the responsibility of the buyer to notify Glass Flooring Systems Inc. prior to ordering if the project requires an engineering report or stamped drawings.
B133: Exclusions (from Base Price)
B134: - Shipping | G134: - Waterproofing connection to frames
B135: - Installation | G135: - Preparation of openings
B136: - Engineering | G136: - Structural steel
B137: - Unloading labor and material handling equipment at jobsite | G137: - LED lighting and wiring
...

Sheet Proposal Descriptions
A4: Series 1000 Pedestal TB FA | B4: Thank you for your interest in Glass Flooring Systems. The following quote is for (X) XX" x XX" fully assembled ICC approved Series 1000 SkyFloor® walkable skylights. These are complete units which consist of our proprietary, thermally broken structural pedestal framing with integrated setting gasket and structural walkable glass panels with tested anti-slip top layer. They come fully assembled with the walkable glass panels bonded to the frames with Dow Corning 995 silicone. The make up of the glass panels is listed below. Please review and let us know if you have any questions or need any additional information.
A5: Series 1000 Pedestal TB KD | B5: Thank you for your interest in Glass Flooring Systems. The following quote is for (X) XX" x XX" ICC approved Series 1000 SkyFloor® walkable skylights. These are complete systems which consist of our proprietary, thermally broken structural pedestal framing with integrated setting gaskets and structural walkable glass panels with tested anti-slip top layer. The make up of the glass panels is listed below. Please review and let us know if you have any questions or need any additional information.
A6: Series 1000 Recessed TB FA | B6: Thank you for your interest in Glass Flooring Systems. The following quote is for (X) XX" x XX" fully assembled ICC approved Series 1000 SkyFloor® walkable skylights. These are complete units which consist of our proprietary structural, thermally broken, recessed framing with integrated setting gaskets, LED light channel and structural walkable glass panels with tested anti-slip top layer. They come fully assembled with the walkable glass panels bonded to the frames with Dow Corning 995 silicone. The make up of the glass panels is listed below. Please review and let us know if you have any questions or need any additional information.
A7: Series 1000 Recessed TB KD | B7: Thank you for your interest in Glass Flooring Systems. The following quote is for (X) XX" x XX" ICC approved Series 1000 SkyFloor® walkable skylights. These are complete systems which consist of our proprietary structural, thermally broken, recessed framing with integrated setting gaskets and structural walkable glass panels with tested anti-slip top layer. The make up of the glass panels is listed below. Please review and let us know if you have any questions or need any additional information.
A8: Series 1000 Interior Recessed FA | B8: Thank you for your interest in Glass Flooring Systems. The following quote is for (X) XX" x XX" fully assembled SkyFloor® interior glass flooring system. This is a complete system consisting of the walkable glass panels with tested anti-slip texture and our structural recessed interior floor framing with integrated setting gaskets and LED light channel. The make up of the glass panels is listed below. Please review and let us know if you have any questions or need any additional information.
A9: Series 1000 Interior Recessed KD | B9: Thank you for your interest in Glass Flooring Systems. The following quote is for (X) XX" x XX" SkyFloor® interior glass flooring system. This is a complete system consisting of the walkable glass panels with tested anti-slip texture and our structural recessed interior floor framing with integrated setting gaskets and LED light channel. The make up of the glass panels is listed below. Please review and let us know if you have any questions or need any additional information.
A10: EconoFrame and Gasket | B10: Thank you for your interest in Glass Flooring Systems. The following quote is for (X) XX" x XX" walkable glass panels with tested anti-slip top surface. Also, included with the glass panel pricing is a add option for our EconoFrame® with integrated setting gasket. The eFrame will come to you in 12 ft. lengths and will need to be cut to size by installer. Our EconoFrame™ is an easy and elegant solution for setting walkable glass panels onto existing structural framing. The make up of the glass panels is listed below. Please review and let us know if you have any questions or need any additional information.
A11: EconoFrame cut to size | B11: Thank you for your interest in Glass Flooring Systems. The following quote is for (X) XX" x XX" walkable glass panels with tested anti-slip top surface. Also, included with the glass panels is our EconoFrame® cut to size with integrated setting gasket. Our EconoFrame® is an easy and elegant solution for setting walkable glass panels onto existing structural framing. The make up of the glass panels is listed below. Please review and let us know if you have any questions or need any additional information.
A12: Just Glass | B12: Thank you for your interest in Glass Flooring Systems. The following quote is for (X) XX" x XX" walkable glass panels. Each structural walkable glass panels has a tested anti-slip top layer. The make up of the glass panels is listed below. Please review and let us know if you have any questions or need any additional information.
A13: Stair Treads | B13: Thank you for your interest in Glass Flooring Systems. The following quote is for (X) XX" x XX" glass stair treads. All stair tread edges are post lamination polished for an ultra clear finished edge. The make up of the glass treads is listed below. Please review and let us know if you have any questions or need any additional information.
A14: Deck | B14: Thank you for your interest in Glass Flooring Systems. The following quote is for a XX" x XX" SkyFloor® glass deck system. This is a complete deck system consisting of the walkable glass panels with tested anti-slip texture and our structural deck framing with integrated setting gaskets, LED light channel and (xx) linear feet of integrated (glass cable) railing. The make up of the glass panels is listed below. Please review and let us know if you have any questions or need any additional information.
A15: Series 2000 Pedestal TB FA | B15: Thank you for your interest in Glass Flooring Systems. The following quote is for (X) XX" x XX" fully assembled ICC approved Series 2000 SkyFloor® ultra high performance walkable skylights. These are complete units which consist of our proprietary, thermally broken structural pedestal framing with integrated gutter and weep system, setting gaskets and structural walkable glass panels with tested anti-slip top layer. They come fully assembled with the walkable glass panels bonded to the frames with Dow Corning 995 silicone. The make up of the glass panels is listed below. Please review and let us know if you have any questions or need any additional information.
... A29: Interior Recessed Knock Down | B29: 6063-T6 extruded aluminum, interior recessed perimeter framing with integrated LED lighting channel. Unit to be assembled and glazed on site.
B30: 6063-T6 extruded aluminum non-structural EconoFrame® perimeter framing with integrated LED lighting channel. Finish is a painted black. The EconoFrame® is not designed as waterproofed system - please let estimating know if this is a project requirement. This material is available as a fully welded frame at an additional cost.
A31: EconoFrame Cut to Size | B31: 6063-T6 extruded aluminum non-structural EconoFrame® perimeter framing with integrated LED lighting channel. Cut to size. Finish is a painted black. The EconoFrame® is not designed as waterproofed system - please let estimating know if this is a project requirement. This material is available as a fully welded frame at an additional cost.
B32: Framing is not included in this proposal.
B33: Framing is not included in this proposal.
A34: Deck Perimeter | B34: 6063-T6 extruded aluminum, deck perimeter framing with integrated LED lighting channel.
B36: Hide this, frame finish and EconoFrame info - Not being used
B38: Installation by certified Glass Flooring Systems contractor. This will be a separate contract between owner and installer. Add $xxxxx
B39: Initial here ________ if you require installation and approve additional charge as noted.
A42: Typical | B42: Lead time is dependent on the anti-slip texture selected. Currently our lead time is 4 - 5 weeks for in stock textures and 10-12 weeks for textures not currently in stock. Please check with us for availability - Lead times are from approved shop drawings.
A45: Expedited Orders | B45: Lead times are dependent on the anti-slip texture decided upon. Currently, our lead time is 10 - 12 weeks from approved shop drawings. We are able to expedite orders, which contain readily available anti-slip textures, for an additional fee . Expedited orders have a 4-6 week lead time from approved shops.
A49: IGU's (anything from control) | B49: lead time 14 - 16 weeks after approved shop drawings but can vary depending on market conditions. See our terms and conditions for more information.
B51: 10mm top layer – low iron tempered Sevasa anti-slip texture. Final texture TBD.
B52: .060 interlayer PVB
B53: 10mm middle layer – low iron tempered
B54: .060 interlayer PVB
B55: 10mm bottom layer – low iron tempered
A58: Engineering Descriptions
A59: Glass only
A60: Glass and frame
A61: Stamped drawings

Sheet Transmittal
A1: Glass Flooring Systems, Inc.
A2: 6 Aaron Way Sparta, NJ 07871 - Phone (862) 701-5320
B5: Transmittal
I8: Date: | K8: Project #:
B9: Deliver To:
I11: Project:
B13: Attn:
B16: We are sending you
C18: Shop Drawings | F18: Sky Floor™ unit
C20: Frame Sample | F20: Test Unit
C22: Glass Sample | F22: For Review
C24: Specifications | F24: For Approval
C28: Qty | D28: Date | E28: Paint Color | G28: Revisions | H28: Description
C43: Sent by: | D43: Danielle Fisher

Sheet Invoice
J3: Invoice Order # | K3: 10206
J4: Date: | K4: =TODAY()
J5: Project Name: | K5: =#REF!
H6: Project Address: | K6: =#REF!
J7: Contact: | K7: =#REF!
J8: Phone: | K8: =#REF!
J9: Email: | K9: =#REF!
B10: 6 Aaron Way Sparta, NJ 07871
B11: www.glassflooringsystems.com
A15: Invoice Order #10206
C18: =#REF!
C19: =#REF!
C20: Contact person: | E20: =#REF!
C21: Phone: | D21: =#REF!
C30: One 24 x 24 Sky Floor walk on skylight
C39: Thank You for choosing Glass Floor System, Inc.
C41: Greg Muniz
C42: greg@glassflooringsystems.com
A54: www.glassflooringsystems.com
A55: 6 Aaron Way Sparta, NJ 07871
A56: 862-701-5320

Sheet Change Order
B2: Change Order
J4: Change Order # | N4: =#REF! & " CO"
J5: Date: | N5: =TODAY()
J6: Project Name: | N6: =#REF!
J7: Project Address: | N7: =#REF!
J8: Contact: | N8: Dan Muniz
J9: Email: | N9: dan@glassflooringsystems.com
B11: 6 Aaron Way Sparta, NJ 07871
B12: 862-701-5320
B13: www.glassflooringsystems.com
B18: Customer
B19: =#REF!
B20: =#REF!
B21: Attn: | C21: =#REF!
B25: Qty | D25: Description | K25: Price | N25: Amount
K26: 0 | N26: =B26*K26
K27: 0 | N27: =B27*K27
K28: 0 | N28: =B28*K28
K29: 0 | N29: =B29*K29
K30: 0 | N30: =B30*K30
K31: 0 | N31: =B31*K31
K32: 0 | N32: =B32*K32
K33: 0 | N33: =B33*K33
K34: 0 | N34: =B34*K34
K35: 0 | N35: =B35*K35
K36: 0 | N36: =B36*K36
B37: Note: This change order becomes part of and in conformance with the existing contract
E39: We agree to the changes specified above at this price | N39: =SUM(N26:N36)
E40: Previous contract amount | N40: =Proposal!#REF!
E41: Revised contract price | N41: =N40+N39
B48: Accepted - The above prices and specifications of this change order are satisfactory and are hereby accepted. All work to be performed under same terms and conditions as specified in original contract unless otherwise stipulated.
B55: Signature -
B57: Date of acceptance -

Sheet Claim Form
B2: Claim Invoice
J5: Date: | N5: =TODAY()
J6: Project Name: | N6: =#REF!
J7: Project Address: | N7: =#REF!
J8: Contact: | N8: Greg Muniz
J9: Email: | N9: greg@glassflooringsystems.com
M10: Claim #
B11: 6 Aaron Way Sparta, NJ 07981
B12: 862-701-5320
B13: www.glassflooringsystems.com
B18: Customer
B19: =#REF!
B20: =#REF!
B21: Attn: | C21: =#REF!
B25: Qty | D25: Description | K25: Price | N25: Amount
K26: 0 | N26: =B26*K26
K27: 0 | N27: =B27*K27
K28: 0 | N28: =B28*K28
K29: 0 | N29: =B29*K29
K30: 0 | N30: =B30*K30
K31: 0 | N31: =B31*K31
K32: 0 | N32: =B32*K32
K33: 0 | N33: =B33*K33
K34: 0 | N34: =B34*K34
K35: 0 | N35: =B35*K35
K36: 0 | N36: =B36*K36
B37: Note: This change order becomes part of and in conformance with the existing contract
E39: We agree to the changes specified above at this price | N39: =SUM(N26:N36)
E40: Previous contract amount | N40: =Proposal!#REF!
E41: Revised contract price | N41: =N40+N39
B48: Accepted - The above prices and specifications of this change order are satisfactory and are hereby accepted. All work to be performed under same terms and conditions as specified in original contract unless otherwise stipulated.
B55: Signature -
B57: Date of acceptance -

Sheet Purchase Order
A2: Purchase Order
O3: Lucid
I4: Purchase Order # | M4: 11076 | O4: Control
I5: Date: | M5: =TODAY() | O5: Eastern Glass
I6: Project Name: | M6: RoboPac Repair | O6: Quality Metal
I7: Project Address: | O7: Intuitive Powder Coating | P7: Y
I8: Contact: | M8: Greg Muniz | O8: Bonnell
I9: Email: | M9: greg@glassflooringsystems.com | O9: Lauren Manufacturing
O10: Purchase order # | P10: 10141
A11: 6 Aaron Way Sparta, NJ 07871 862-701-5320 | O11: ="Purchase Order #"&P10
A12: www.glassflooringsystems.com
A17: Vendor | J17: Ship To
A18: ROBOPAC USA Valentina Ferrari | J18: Glass Flooring Systems 6 Aaron Way Sparta, NJ 07871 Attn: Greg Muniz 862-701-5320 | O18: Lucid Glass Studio 76 Amarai Street East Providence, Rhode Island 02915 Attn: Clint Hopkins 401-434-1277 | P18: Control Glass, Acustico y Solar, S.L. POL. Ind La Paz, Oporto, 4 44195 Teruel Spain Attn: Alvaro del Rio +34628067281 | Q18: Eastern Glass Resources, Inc. 770 Supor Boulevard Harrison, NJ 07029 Attn: Max Fisher 973-483-8411 | R18: Quality Metal Finishing 80 George Street Paterson, NJ 07503 Attn: Brad 973-345-0963 | S18: Intuitive Powder Coating 100 Hibernia Ave. Rockaway, NJ 07866 Attn: Chris Ruhren 862-432-7851 | T18: Bonnell Aluminum 25 Bonnell Street PO Box 428 Newnan Georgia 30263 Attn: Kristen Avery 615-683-2922 | U18: Lauren Manufacturing 2228 Reiser Ave New Philadelphia, Ohio 44663 Attn: Catherine Moss 330-339-3373
A20: =IF(P3="Y","Clint",IF(P4="Y","Alvaro",IF(P5="Y","Joe","")))
A22: Approval to schedule technician on Thursday 9/15/22 to repair inopperable RoboPac Machine. Quote #412 REV
A42: Thank You
A44: Greg Muniz
A45: greg@glassflooringsystems.com

Sheet Packing List
A1: Glass Flooring Systems, Inc.
A2: 6 Aaron Way Sparta, NJ 07871 - Phone (862) 701-5320
B5: Packing List
H8: Date: | I8: =TODAY() | J8: Project #: | K8: =#REF!
B9: To: | C9: =#REF!
C10: =#REF! | H10: Project Name: | I10: =#REF!
H11: Address: | I11: =#REF!
B13: Attention: | D13: =#REF!
D14: =#REF!
B16: We are sending you
C18: Shop Drawings | F18: Sky Floor™ unit
C20: Paint Sample | E20: X | F20: Test Unit
C22: Glass Sample | F22: For Review
C24: Specifications | F24: For Approval
C28: Qty | D28: Date | E28: Paint Color | G28: Revisions | H28: Description
B56: Sent by: | D56: Greg Muniz

Sheet Weights - Descriptions
A3: Frame | D3: lb./ft. | E3: Unit 1 | F3: Unit 2 | G3: Unit 3 | H3: Unit 4 | I3: Unit 5 | J3: Unit 6 | K3: Unit 7 | L3: Unit 8 | M3: Unit 9 | N3: Unit 10
B4: Perimeter*
B5: Pedestal perimeter thermally broken | C5: GFS-5 | D5: =7.673+D25+D24 | E5: ='Pricing Worksheet'!E37*'Weights - Descriptions'!$D$5 | F5: ='Pricing Worksheet'!H$37*'Weights - Descriptions'!$D$5 | G5: ='Pricing Worksheet'!K$37*'Weights - Descriptions'!$D$5 | H5: ='Pricing Worksheet'!N$37*'Weights - Descriptions'!$D$5 | I5: ='Pricing Worksheet'!Q$37*'Weights - Descriptions'!$D$5 | J5: ='Pricing Worksheet'!T$37*'Weights - Descriptions'!$D$5 | K5: ='Pricing Worksheet'!W$37*'Weights - Descriptions'!$D$5 | L5: ='Pricing Worksheet'!Z$37*'Weights - Descriptions'!$D$5 | M5: ='Pricing Worksheet'!AC$37*'Weights - Descriptions'!$D$5 | N5: ='Pricing Worksheet'!AF$37*'Weights - Descriptions'!$D$5
B6: Recessed perimeter thermally broken | C6: GFS-6 | D6: =8.524+D25+D24 | E6: ='Pricing Worksheet'!E38*'Weights - Descriptions'!$D$6 | F6: ='Pricing Worksheet'!H$38*'Weights - Descriptions'!$D$6 | G6: ='Pricing Worksheet'!K$38*'Weights - Descriptions'!$D$6 | H6: ='Pricing Worksheet'!N$38*'Weights - Descriptions'!$D$6 | I6: ='Pricing Worksheet'!Q$38*'Weights - Descriptions'!$D$6 | J6: ='Pricing Worksheet'!T$38*'Weights - Descriptions'!$D$6 | K6: ='Pricing Worksheet'!W$38*'Weights - Descriptions'!$D$6 | L6: ='Pricing Worksheet'!Z$38*'Weights - Descriptions'!$D$6 | M6: ='Pricing Worksheet'!AC$38*'Weights - Descriptions'!$D$6 | N6: ='Pricing Worksheet'!AF$38*'Weights - Descriptions'!$D$6
B7: Recessed Perimeter non thermally broken | C7: GFS-4 | D7: 7.973 | E7: ='Pricing Worksheet'!E39*'Weights - Descriptions'!$D$7 | F7: ='Pricing Worksheet'!H$39*'Weights - Descriptions'!$D$7 | G7: ='Pricing Worksheet'!K$39*'Weights - Descriptions'!$D$7 | H7: ='Pricing Worksheet'!N$39*'Weights - Descriptions'!$D$7 | I7: ='Pricing Worksheet'!Q$39*'Weights - Descriptions'!$D$7 | J7: ='Pricing Worksheet'!T$39*'Weights - Descriptions'!$D$7 | K7: ='Pricing Worksheet'!W$39*'Weights - Descriptions'!$D$7 | L7: ='Pricing Worksheet'!Z$39*'Weights - Descriptions'!$D$7 | M7: ='Pricing Worksheet'!AC$39*'Weights - Descriptions'!$D$7 | N7: ='Pricing Worksheet'!AF$39*'Weights - Descriptions'!$D$7
B8: Deck perimeter | C8: GFS-13 | D8: 10.297 | E8: ='Pricing Worksheet'!E$44*'Weights - Descriptions'!$D$8 | F8: ='Pricing Worksheet'!H$44*'Weights - Descriptions'!$D$8 | G8: ='Pricing Worksheet'!K$44*'Weights - Descriptions'!$D$8 | H8: ='Pricing Worksheet'!N$44*'Weights - Descriptions'!$D$8 | I8: ='Pricing Worksheet'!Q$44*'Weights - Descriptions'!$D$8 | J8: ='Pricing Worksheet'!T$44*'Weights - Descriptions'!$D$8 | K8: ='Pricing Worksheet'!W$44*'Weights - Descriptions'!$D$8 | L8: ='Pricing Worksheet'!Z$44*'Weights - Descriptions'!$D$8 | M8: ='Pricing Worksheet'!AC$44*'Weights - Descriptions'!$D$8 | N8: ='Pricing Worksheet'!AF$44*'Weights - Descriptions'!$D$8
B9: Series 2000 Pedestal | C9: GFS-15 | D9: 5.785 | E9: ='Pricing Worksheet'!E$40*'Weights - Descriptions'!$D$9 | F9: ='Pricing Worksheet'!H$40*'Weights - Descriptions'!$D$9 | G9: ='Pricing Worksheet'!K$40*'Weights - Descriptions'!$D$9 | H9: ='Pricing Worksheet'!N$40*'Weights - Descriptions'!$D$9 | I9: ='Pricing Worksheet'!Q$40*'Weights - Descriptions'!$D$9 | J9: ='Pricing Worksheet'!T$40*'Weights - Descriptions'!$D$9 | K9: ='Pricing Worksheet'!W$40*'Weights - Descriptions'!$D$9 | L9: ='Pricing Worksheet'!Z$40*'Weights - Descriptions'!$D$9 | M9: ='Pricing Worksheet'!AC$40*'Weights - Descriptions'!$D$9 | N9: ='Pricing Worksheet'!AF$40*'Weights - Descriptions'!$D$9
B10: Series 2000 Recessed | C10: GFS-16 | D10: 6.371 | E10: ='Pricing Worksheet'!E$41*'Weights - Descriptions'!$D$10 | F10: ='Pricing Worksheet'!H$41*'Weights - Descriptions'!$D$10 | G10: ='Pricing Worksheet'!K$41*'Weights - Descriptions'!$D$10 | H10: ='Pricing Worksheet'!N$41*'Weights - Descriptions'!$D$10 | I10: ='Pricing Worksheet'!Q$41*'Weights - Descriptions'!$D$10 | J10: ='Pricing Worksheet'!T$41*'Weights - Descriptions'!$D$10 | K10: ='Pricing Worksheet'!W$41*'Weights - Descriptions'!$D$10 | L10: ='Pricing Worksheet'!Z$41*'Weights - Descriptions'!$D$10 | M10: ='Pricing Worksheet'!AC$41*'Weights - Descriptions'!$D$10 | N10: ='Pricing Worksheet'!AF$41*'Weights - Descriptions'!$D$10
B12: Rafters
B13: T Rafter non-thermal | C13: GFS-1 | D13: 6.77 | E13: ='Pricing Worksheet'!E53*'Weights - Descriptions'!$D$13 | F13: ='Pricing Worksheet'!H$53*'Weights - Descriptions'!$D$13 | G13: ='Pricing Worksheet'!K$53*'Weights - Descriptions'!$D$13 | H13: ='Pricing Worksheet'!N$53*'Weights - Descriptions'!$D$13 | I13: ='Pricing Worksheet'!Q$53*'Weights - Descriptions'!$D$13 | J13: ='Pricing Worksheet'!T$53*'Weights - Descriptions'!$D$13 | K13: ='Pricing Worksheet'!W$53*'Weights - Descriptions'!$D$13 | L13: ='Pricing Worksheet'!Z$53*'Weights - Descriptions'!$D$13 | M13: ='Pricing Worksheet'!AC$53*'Weights - Descriptions'!$D$13 | N13: ='Pricing Worksheet'!AF$53*'Weights - Descriptions'!$D$13
B14: I Rafter non-thermal | C14: GFS-7 | D14: 9.626 | E14: ='Pricing Worksheet'!E54*'Weights - Descriptions'!$D$14 | F14: ='Pricing Worksheet'!H$54*'Weights - Descriptions'!$D$14 | G14: ='Pricing Worksheet'!K$54*'Weights - Descriptions'!$D$14 | H14: ='Pricing Worksheet'!N$54*'Weights - Descriptions'!$D$14 | I14: ='Pricing Worksheet'!Q$54*'Weights - Descriptions'!$D$14 | J14: ='Pricing Worksheet'!T$54*'Weights - Descriptions'!$D$14 | K14: ='Pricing Worksheet'!W$54*'Weights - Descriptions'!$D$14 | L14: ='Pricing Worksheet'!Z$54*'Weights - Descriptions'!$D$14 | M14: ='Pricing Worksheet'!AC$54*'Weights - Descriptions'!$D$14 | N14: ='Pricing Worksheet'!AF$54*'Weights - Descriptions'!$D$14
B15: T Rafter thermally Broken | D15: =D13+D25 | E15: ='Pricing Worksheet'!E51*'Weights - Descriptions'!$D$15 | F15: ='Pricing Worksheet'!H$51*'Weights - Descriptions'!$D$15 | G15: ='Pricing Worksheet'!K$51*'Weights - Descriptions'!$D$15 | H15: ='Pricing Worksheet'!N$51*'Weights - Descriptions'!$D$15 | I15: ='Pricing Worksheet'!Q$51*'Weights - Descriptions'!$D$15 | J15: ='Pricing Worksheet'!T$51*'Weights - Descriptions'!$D$15 | K15: ='Pricing Worksheet'!W$51*'Weights - Descriptions'!$D$15 | L15: ='Pricing Worksheet'!Z$51*'Weights - Descriptions'!$D$15 | M15: ='Pricing Worksheet'!AC$51*'Weights - Descriptions'!$D$15 | N15: ='Pricing Worksheet'!AF$51*'Weights - Descriptions'!$D$15
B16: I Rafter thermally broken | D16: =D14+D25 | E16: ='Pricing Worksheet'!E52*'Weights - Descriptions'!$D$16 | F16: ='Pricing Worksheet'!H$52*'Weights - Descriptions'!$D$16 | G16: ='Pricing Worksheet'!K$52*'Weights - Descriptions'!$D$16 | H16: ='Pricing Worksheet'!N$52*'Weights - Descriptions'!$D$16 | I16: ='Pricing Worksheet'!Q$52*'Weights - Descriptions'!$D$16 | J16: ='Pricing Worksheet'!T$52*'Weights - Descriptions'!$D$16 | K16: ='Pricing Worksheet'!W$52*'Weights - Descriptions'!$D$16 | L16: ='Pricing Worksheet'!Z$52*'Weights - Descriptions'!$D$16 | M16: ='Pricing Worksheet'!AC$52*'Weights - Descriptions'!$D$16 | N16: ='Pricing Worksheet'!AF$52*'Weights - Descriptions'!$D$16
B17: I Beam Series 2000 | C17: GFS-17 | D17: 9.289 | E17: ='Pricing Worksheet'!E$56*'Weights - Descriptions'!$D$17 | F17: ='Pricing Worksheet'!H$56*'Weights - Descriptions'!$D$17 | G17: ='Pricing Worksheet'!K$56*'Weights - Descriptions'!$D$17 | H17: ='Pricing Worksheet'!N$56*'Weights - Descriptions'!$D$17 | I17: ='Pricing Worksheet'!Q$56*'Weights - Descriptions'!$D$17 | J17: ='Pricing Worksheet'!T$56*'Weights - Descriptions'!$D$17 | K17: ='Pricing Worksheet'!W$56*'Weights - Descriptions'!$D$17 | L17: ='Pricing Worksheet'!Z$56*'Weights - Descriptions'!$D$17 | M17: ='Pricing Worksheet'!AC$56*'Weights - Descriptions'!$D$17 | N17: ='Pricing Worksheet'!AF$56*'Weights - Descriptions'!$D$17
B18: T Rafter Series 2000
B20: Fasteners | D20: 0.21 | E20: ='Pricing Worksheet'!E61*'Weights - Descriptions'!$D$20 | F20: ='Pricing Worksheet'!H61*'Weights - Descriptions'!$D$20 | G20: ='Pricing Worksheet'!K61*'Weights - Descriptions'!$D$20 | H20: ='Pricing Worksheet'!N61*'Weights - Descriptions'!$D$20 | I20: ='Pricing Worksheet'!Q61*'Weights - Descriptions'!$D$20 | J20: ='Pricing Worksheet'!T61*'Weights - Descriptions'!$D$20 | K20: ='Pricing Worksheet'!W61*'Weights - Descriptions'!$D$20 | L20: ='Pricing Worksheet'!Z61*'Weights - Descriptions'!$D$20 | M20: ='Pricing Worksheet'!AC61*'Weights - Descriptions'!$D$20 | N20: ='Pricing Worksheet'!AF61*'Weights - Descriptions'!$D$20
B21: Brackets | D21: 0.25 | E21: ='Pricing Worksheet'!E60*'Weights - Descriptions'!$D$21 | F21: ='Pricing Worksheet'!H60*'Weights - Descriptions'!$D$21 | G21: ='Pricing Worksheet'!K60*'Weights - Descriptions'!$D$21 | H21: ='Pricing Worksheet'!N60*'Weights - Descriptions'!$D$21 | I21: ='Pricing Worksheet'!Q60*'Weights - Descriptions'!$D$21 | J21: ='Pricing Worksheet'!T60*'Weights - Descriptions'!$D$21 | K21: ='Pricing Worksheet'!W60*'Weights - Descriptions'!$D$21 | L21: ='Pricing Worksheet'!Z60*'Weights - Descriptions'!$D$21 | M21: ='Pricing Worksheet'!AC60*'Weights - Descriptions'!$D$21 | N21: ='Pricing Worksheet'!AF60*'Weights - Descriptions'!$D$21
B22: Totals | E22: =SUM(E5:E21) | F22: =SUM(F5:F21) | G22: =SUM(G5:G21) | H22: =SUM(H5:H21) | I22: =SUM(I5:I21) | J22: =SUM(J5:J21) | K22: =SUM(K5:K21) | L22: =SUM(L5:L21) | ... N22: =SUM(N5:N21)
B24: *perimeter includes cap | D24: 0.394
B25: *thermally broken includes blocks | D25: 0.418
B26: 2.0 Perimeter Gutter | C26: GFS-18 | D26: 1.246
B27: Main Gutter | C27: GFS-20 | D27: 0.638
B28: 2" horizontal cap | C28: GFS-24 | D28: 1.117
B29: 3" Vertical cap | C29: GFS-25 | D29: 1.164
B33: SkyFloor™ thermally broken walkable skylight
B35: Walkable glass flooring
B38: Sales tax
B39: Plus tax if applicable

Sheet Railings
B3: Railing Counts
B5: Short | C5: Long | D5: Qty
B6: 0 | C6: 1 | D6: ='Pricing Worksheet'!K113+2
B7: 0 | C7: 2 | D7: ='Pricing Worksheet'!K113*2+4
B8: 1 | C8: 0 | D8: ='Pricing Worksheet'!L113+2
B9: 1 | C9: 1 | D9: ='Pricing Worksheet'!K113+'Pricing Worksheet'!L113+3
B10: 1 | C10: 2 | D10: ='Pricing Worksheet'!K113*2+'Pricing Worksheet'!L113+4
B11: 2 | C11: 0 | D11: ='Pricing Worksheet'!L113*2+4
B12: 2 | C12: 1 | D12: ='Pricing Worksheet'!K113+'Pricing Worksheet'!L113*2+4
B13: 2 | C13: 2 | D13: ='Pricing Worksheet'!K113*2+'Pricing Worksheet'!L113*2+4

Sheet Bonnell - Glass Pricing
B2: PRICING UPDATED 5-13-22
J3: Paint Options
D4: Weight lb./ft. | E4: Unit Price per lb. | F4: Cost per ft. | G4: Total Cost Per Ft | H4: 0.05 | I4: 0.1 | J4: Paint - non standard colors | K4: HPP - 50% Kynar | L4: HPP - 70% non Exotic | M4: Alodine
A6: GFS 9-1 | B6: EconoFrame perimeter | D6: 1.295 | E6: 3.6 | F6: =(D6*E6)+L6 | I6: =(F6*$I$4)+F6 | J6: 0.275 | K6: 0.61 | L6: 0.969
A7: GFS 11-1 | B7: EconoFrame 2.5 | D7: 0.787 | E7: 3.6 | F7: =(D7*E7)+L7 | I7: =(F7*$I$4)+F7 | J7: 0.275 | K7: 0.402 | L7: 0.724
A8: GFS 10-1 | B8: EconoFrame 3.0 | D8: 0.937 | E8: 3.6 | F8: =(D8*E8)+L8 | I8: =(F8*$I$4)+F8 | J8: 0.275 | K8: 0.459 | L8: 0.724
A10: GFS1-1 | B10: T Section NTB | D10: 6.77 | E10: 3.6 | F10: =(D10*E10)+M10 | G10: =F10 | H10: =(G10*$H$4)+G10 | I10: =(G10*$I$4)+G10 | M10: 0.663
B11: T Section TB | E11: 3.6 | G11: =F10+F18+M11 | H11: =(G11*$H$4)+G11 | I11: =(G11*$I$4)+G11 | M11: 0.663
A12: GFS 7-1 | B12: I Beam NTB | D12: 9.957 | E12: 3.6 | F12: 32.12 | G12: =F12 | H12: =(G12*$H$4)+G12 | I12: =(G12*$I$4)+G12 | M12: 0.797
B13: I Beam TB | G13: =F12+F18+M13 | H13: =(G13*$H$4)+G13 | I13: =(G13*$I$4)+G13 | M13: 0.797
A14: GFS 5-1 | B14: Pedestal Perimeter TB | D14: 7.673 | E14: 3.6 | F14: 28 | G14: =F14+F17+F19 | H14: =(G14*$H$4)+G14 | I14: =(G14*$I$4)+G14
A15: GFS 6-1 | B15: Recessed Perimeter TB | D15: 8.524 | E15: 3.6 | F15: 35.31 | G15: =F15+F17+F19+M15 | H15: =(G15*$H$4)+G15 | I15: =(G15*$I$4)+G15 | M15: 0.959
A16: GFS 4-1 | B16: Recessed perimeter NTB | D16: 8.05 | E16: 3.6 | F16: 29.5 | G16: =F16 | H16: =(G16*$H$4)+G16 | I16: =(G16*$I$4)+G16 | M16: 0.959
A17: GFS 3-1 | B17: Adjustable cap | D17: 0.394 | E17: 3.6 | F17: =D17*E17 | H17: =(F17*$H$4)+F17 | I17: =(F17*$I$4)+F17
A18: GFS 2-1 | B18: Snap in block | D18: 0.418 | E18: 3.6 | F18: =D18*E18 | H18: =(F18*$H$4)+F18 | I18: =(F18*$I$4)+F18
A19: GFS 8-1 | B19: Perimeter snap in | D19: 0.49 | E19: 3.6 | F19: =D19*E19 | H19: =(F19*$H$4)+F19 | I19: =(F19*$I$4)+F19
A20: GFS 13-1 | B20: Deck perimeter | D20: 10.297 | E20: 3.6 | F20: 38.5 | G20: =F20 | H20: =(G20*$H$4)+G20 | I20: =(F20*$I$4)+F20
A21: GFS 14 | B21: Adjustable cap with flange | E21: 3.6
A22: GFS 15 | B22: 2000 Series pedestal leg | D22: 5.785 | E22: 3.6 | F22: =E22*D22 | H22: =(F22*$H$4)+F22 | I22: =(F22*$I$4)+F22
A23: GFS 16 | B23: 2000 Series recessed leg | D23: 6.371 | E23: 3.6 | F23: 24.65 | H23: =(F23*$H$4)+F23 | I23: =(F23*$I$4)+F23
A24: GFS 17 | B24: 2000 Series I beam | D24: 9.289 | E24: 3.6 | F24: 34.33 | H24: =(F24*$H$4)+F24 | I24: =(F24*$I$4)+F24
A25: GFS 18 | B25: 2000 Series perimeter gutter | D25: 1.246 | E25: 3.6 | F25: =E25*D25 | H25: =(F25*$H$4)+F25 | I25: =(F25*$I$4)+F25
A26: GFS 19
A27: GFS 20 | B27: 2000 Series snap in - main gutter | D27: 0.638 | E27: 3.6 | F27: =E27*D27 | H27: =(F27*$H$4)+F27 | I27: =(F27*$I$4)+F27
A28: GFS 21 | B28: 2000 Series sanp in - secondary gutter | D28: 0.673 | E28: 3.6 | F28: =E28*D28 | H28: =(F28*$H$4)+F28 | I28: =(F28*$I$4)+F28
A29: GFS 22 | B29: 2000 Sereis seam stop | D29: 0.179 | E29: 3.6 | F29: =E29*D29 | H29: =(F29*$H$4)+F29 | I29: =(F29*$I$4)+F29
A30: GFS 23 | B30: 2000 Series cap with extension | D30: 0.469 | E30: 3.6 | F30: =E30*D30 | H30: =(F30*$H$4)+F30 | I30: =(F30*$I$4)+F30
A31: GFS24 | B31: Adjustable cap with 2" horizontal extension | D31: 1.117 | E31: 3.6 | F31: =E31*D31 | H31: =(F31*$H$4)+F31 | I31: =(F31*$I$4)+F31
A32: GFS25 | B32: Adjustable cap with 3" vertical extension | D32: 1.164 | E32: 3.6 | F32: =E32*D32 | H32: =(F32*$H$4)+F32 | I32: =(F32*$I$4)+F32
A34: GFS33 | B34: Series 3000 top | D34: 1.847 | E34: 2.695 | F34: =E34*D34 | G34: =F34+L34 | L34: 2.372
A35: GFS34 | B35: Series 3000 base | D35: 1.248 | E35: 2.735 | F35: =E35*D35 | G35: =F35+L35 | L35: 1.06
A36: GFS35 | B36: Series 3000 hollow tube | D36: 0.355 | E36: 2.775 | F36: =E36*D36 | G36: =F36+L36 | L36: 0.935
A37: GFS36 | B37: Series 3000 Screw Cover | G37: 1
B38: Ensinger | G38: 2.25
B39: Total with ensinger and paint | G39: =SUM(G34:G38)
B41: Ensinger Thermal break | F41: 1.75 | G41: 5 | H41: =(G41*$H$4)+G41
B43: Perimeter gasket - SB1 | G43: 1.56 | H43: =(G43*$H$4)+G43 | I43: =(G43*$I$4)+G43
B44: Cross beam gasket - SB2 | G44: 1.35 | H44: =(G44*$H$4)+G44 | I44: =(G44*$I$4)+G44
B46: 2000 Series with pedestal includes gasket | F46: =F22+F25+G41+G43 | G46: =F22+F25+G41+G43 | H46: =(G46*$H$4)+G46
B47: 2000 Series with recessed includes gasket | F47: =F23+F25+G41+G43 | G47: =F23+F25+G41+G43 | H47: =(G47*$H$4)+G47
B48: 2000 Series with plate includes gasket | F48: =F25+G41+G43 | G48: =F25+G41+G43 | H48: =(G48*$H$4)+G48
C50: Cost | D50: Sale Price
B51: Seeded | C51: 25 | D51: 48
B52: Blur | C52: 12 | D52: 23
B53: 10mm Sevas+SG+12mm+SG+12mm /20/4mm Sunt T+6mm | C53: 95
B54: 12mm+GS+12mm+SG+12mm /20/4mm SunT+6mm | C54: 92

Sheet CR Laurence-Sadev Pricing
B1: CR Laurence Parts
B2: Part Number | C2: Description | D2: Price
